Workbook

Sheet 0. Mode d'emploi
A1: Outil de diagnostic - Guide d'utilisateur
A3: 1. Introduction
A25: 2. Utilisation de l'outil
A71: Fin du mode d'emploi

Sheet 1. Questionnaire d'entretien 
R1: Notes & Réponses
E2: Grille d'entretien | F2: Profil des interviewés (mettez un "x" dans la case pour identifier le ou les profils à interroger pour chaque question) | M2: Grille de notation | R2: Réponse 1 | T2: Réponse 2
A3: N° | B3: Niveau | C3: Dimension | D3: Thématique | E3: Question | F3: Profil 1 | G3: Profil 2 | H3: Profil 3 | I3: Profil 4 | J3: Profil 5 | K3: Profil 6 | L3: … (à compléter par la collectivité) | M3: 0 | N3: 1 | O3: 2 | P3: 3 | Q3: 4 | R3: Note (0 à 4, ou N/A) | S3: Réponse aux questions ouvertes / Commentaire | T3: Note (0 à 4, ou N/A) | U3: Réponse aux questions ouvertes / Commentaire
A4: 1 | B4: 1 | C4: 1. Stratégie et Gouvernance | D4: Stratégie globale | E4: L'engagement environnemental et sociétal fait-il partie des valeurs de la collectivité ? | M4: Non | N4: Il s'agit d'un centre d'intérêt de certains agents uniquement mais pas d'une valeur de la collectivité | O4: Il s'agit d'un centre d'intérêt de la plupart des agents mais pas d'une valeur de la collectivité | P4: C'est une valeur secondaire de la collectivité | Q4: C'est une valeur principale de la collectivité
A5: =A4+1 -> 2 | B5: 1 | C5: 1. Stratégie et Gouvernance | D5: Stratégie NR | E5: Avez-vous déjà intégré une dimension écologique à la gestion du numérique dans votre organisation ? | M5: Non | N5: Des initiatives indépendantes/non coordonnées ont été lancées au sein de la DSI seulement | O5: Des initiatives indépendantes/non coordonnées ont été lancées dans certaines directions de la collectivité | P5: Plusieurs initiatives existent et une démarche globale est en cours de définition/lancement | Q5: Une démarche stratégique globale a été lancée et a atteint de premiers objectifs
A6: =A5+1 -> 3 | B6: 1 | C6: 1. Stratégie et Gouvernance | D6: Stratégie NR | E6: Des objectifs de réduction d'impact environnemental du numérique ont-ils été définis ? | M6: Non | N6: Non, mais c'est en cours de définition | O6: Des objectifs spécifiques sont définis mais ils ne sont pas suivis | P6: Des objectifs spécifiques sont définis et suivis dans le cadre d'une démarche RSE centrale | Q6: Des objectifs spécifiques sont définis et suivis au niveau du pôle numérique responsable
A7: =A6+1 -> 4 | B7: 1 | C7: 1. Stratégie et Gouvernance | D7: Stratégie NR | E7: Quelle serait la principale raison qui vous motiverait à inclure des principes Numérique responsable au sein de la collectivité ? | M7: Aucune raison particulière | N7: Lancer une dynamique numérique responsable au sein de la collectivité | O7: Dès à présent répondre aux obligations réglementaires d'ici 2025 | P7: Construire une image plus positive de la collectivité auprès des citoyens, au-delà des obligations réglementaires | Q7: Devenir un acteur actif et leader de changement sociétal, au au-delà des obligations réglementaires et des images à renforcer
A8: =A7+1 -> 5 | B8: 2 | C8: 1. Stratégie et Gouvernance | D8: Stratégie NR | E8: Pilotez-vous des indicateurs de mesure spécifique au numérique responsable ? | M8: Non | N8: Non, mais souhaite le faire | O8: Non, mais en cours de mise en place | P8: Certains indicateurs sont mis en place et pilotés, mais pas pour l'ensemble des activités liées au numérique | Q8: Les indicateurs de mesure sont mis en place et pilotés pour l'ensemble des activités liées au numérique
A9: =A8+1 -> 6 | B9: 1 | C9: 1. Stratégie et Gouvernance | D9: Stratégie NR | E9: La stratégie numérique responsable de la collectivité est-elle déclinée dans chaque direction (DSI, achats, métiers…) ? | M9: Non | N9: Des consignes génériques sont définies au niveau NR et suivies seulement au sein de la DSI | O9: Des consignes génériques sont définies au niveau NR et suivies par les entités | P9: Des objectifs et consignes spécifiques à chaque entités sont définies au niveau NR | Q9: Des objectifs sont définis pour chaque entité au niveau NR, les entités définissent chacune leur stratégie NR
A10: =A9+1 -> 7 | B10: 1 | C10: 1. Stratégie et Gouvernance | D10: Stratégie NR | E10: La stratégie numérique responsable a-t-elle été déclinée dans d'autres documents programmatiques (SPASER, PCAET…) ? | M10: Non | N10: Non, mais en projet | O10: Oui, partiellement | P10: Oui, en grande partie | Q10: Oui ils sont totalement inclus
A11: =A10+1 -> 8 | B11: 1 | C11: 1. Stratégie et Gouvernance | D11: Stratégie NR | E11: Avez-vous un budget spécifique dédié pour une stratégie et des actions Numérique Responsable ? | M11: Non, pas de budget dédié au Numérique Responsable | N11: Budget limité et réparti dans différentes directions (DSI, direction de la transition écologique, etc.) | O11: Budget limité mais dédié au Numérique Responsable | P11: Budget important mais réparti dans différentes directions (DSI, direction de la transition écologique, etc.) | Q11: Budget important dédié au Numérique Responsable
A12: =A11+1 -> 9 | B12: 2 | C12: 1. Stratégie et Gouvernance | D12: Stratégie NR | E12: Comment est réparti le budget Numérique responsable (formations, développement de use cases, territoire connecté et durable, autres) ?
A13: =A12+1 -> 10 | B13: 3 | C13: 1. Stratégie et Gouvernance | D13: Stratégie NR | E13: Votre stratégie Numérique Responsable a-t-elle permis la mise en place de partenariats, la signature d'accords ou l'attribution de certifications / prix ? | M13: Non | N13: Non mais en cours d'identification d'opportunités | O13: Non mais certaines opportunités ont été identifiées pour la mise en place de partenariats / accords | P13: La collectivité a mis en place des partenariats ou s'est déjà engagée via des accords sur sa stratégie NR | Q13: La collectivité a été distinguée par des certifications / prix sur son investissement NR
A14: =A13+1 -> 11 | B14: 3 | C14: 1. Stratégie et Gouvernance | D14: Stratégie NR | E14: Si oui, décrivez les partenariats, accords ou certifications
A15: =A14+1 -> 12 | B15: 2 | C15: 1. Stratégie et Gouvernance | D15: Stratégie NR | E15: Des objectifs de Numérique responsable sont-ils intégrés à vos rapport annuels ? | M15: Non | N15: Non, mais c'est prévu à court terme | O15: Oui, partiellement (inclus dans les objectifs et la stratégie de l'organisation, mais pas détaillé dans la partie comptabilité) | P15: Oui, en grande partie (inclus dans les objectifs et la stratégie de de l'organisation et partiellement inclus dans la partie comptabilité) | Q15: Oui ils sont totalement inclus dans les rapports annuels (ils font intégralement partie des bilans financiers consolidés, ils sont définis dans les objectifs de l'organisation et ils ont leur propre partie dans le rapport annuel de l'organisation)
A16: =A15+1 -> 13 | B16: 2 | C16: 1. Stratégie et Gouvernance | D16: Stratégie NR | E16: Si oui, décrivez les éléments essentiels et l'année de mise en œuvre ?
A17: =A16+1 -> 14 | B17: 1 | C17: 1. Stratégie et Gouvernance | D17: Org. Interne | E17: Dans quelle fonction de la collectivité la dimension écologique du numérique est intégrée ? | M17: N'est pas intégrée | N17: Sera intégrée dans une des fonctions de la collectivité dans un futur proche | O17: Une fonction DSI | P17: Une fonction "Transition écologique" attachée au DGS | Q17: Une fonction transverse rattachée au DGS
A18: =A17+1 -> 15 | B18: 1 | C18: 1. Stratégie et Gouvernance | D18: Org. Interne | E18: Qui est en charge de porter les sujets Numérique Responsable au sein de votre organisation ? | M18: Personne n'est en charge | N18: Une personne porte ces sujets au sein d'une direction à temps partiel | O18: Une personne porte ces sujets au sein d'une direction à temps plein | P18: Une personne porte ces sujets au sein d'une direction à temps plein et elle dispose d'une équipe de contributeurs à temps partiel | Q18: Plusieurs personnes occupent un poste à temps plein dédié au Numérique Responsable
A19: =A18+1 -> 16 | B19: 2 | C19: 1. Stratégie et Gouvernance | D19: Org. Interne | E19: A quel niveau hiérarchique se situe le pôle Numérique Responsable ? | M19: Pas de pôle Numérique Responsable | N19: Le pôle Numérique Responsable n'est pas visible dans la hiérarchie | O19: Le pôle Numérique Responsable est rattaché au niveau d'une sous-direction de la DSI ou d'une autre direction | P19: Le pôle Numérique Responsable est rattaché au niveau de la DSI ou d'une autre direction | Q19: Le pôle Numérique Responsable est rattaché au niveau du DGS / de la Direction générale
A20: =A19+1 -> 17 | B20: 2 | C20: 1. Stratégie et Gouvernance | D20: Org. Interne | E20: Le responsable numérique responsable participe t-il à des comités de pilotage stratégiques au sein de la collectivité ? | M20: Non | N20: Non, mais c'est prévu à court terme | O20: Oui, en interne de son service | P20: Oui, en interne de sa direction | Q20: Oui, en transverse sur l'ensemble de la collectivité
A21: =A20+1 -> 18 | B21: 2 | C21: 1. Stratégie et Gouvernance | D21: Org. Interne | E21: Le pôle Numérique Responsable peut il s'appuyer sur des relais identifiés dans les directions ? | M21: Non | N21: Les personnes sont déjà identifiées mais peu d'échanges ont été menés avec elles sur le sujet du NR | O21: Un groupe de contacts permet de partager quelques informations avec le pôle Numérique Responsable (veille, …) | P21: Des relais diffusent une veille et des bonnes pratiques Numérique Responsable au sein des entités | Q21: Des représentants officiels (champions) du numérique responsable sont identifiés dans les différentes entités et ont une charge dédiée à cette thématique
A22: =A21+1 -> 19 | B22: 3 | C22: 1. Stratégie et Gouvernance | D22: Org. Interne | E22: Faites-vous appel à des prestataires spécialisés dans le Numérique Responsable ? | M22: Non | N22: Non, mais c'est prévu à court terme | O22: Des prestataires potentiels ont déjà été identifiés | P22: Des discussions ont été engagées avec des prestataires potentiels | Q22: Des prestataires ont déjà été sollicités pour accompagner la collectivité
A23: =A22+1 -> 20 | B23: 2 | C23: 1. Stratégie et Gouvernance | D23: AVEC/BYOD | E23: Mettez-vous en place une stratégie "AVEC/BYOD" (Apportez Votre Equipement personnel de Communication/Bring Your Own Device) pour l'équipement informatique type ordinateur portable ? | M23: Non, ne souhaite pas le faire | N23: Non, mais souhaite le faire | O23: Non, mais une réflexion a déjà été engagée | P23: Oui, en cours de mise en place | Q23: Oui, déjà mis en place
A24: =A23+1 -> 21 | B24: 2 | C24: 1. Stratégie et Gouvernance | D24: AVEC/BYOD | E24: Mettez-vous en place une stratégie "AVEC/BYOD" (Apportez Votre Equipement personnel de Communication/Bring Your Own Device) pour l'équipement téléphonique type smartphone ? | M24: Non, ne souhaite pas le faire | N24: Non, mais souhaite le faire | O24: Non, mais une réflexion a déjà été engagée | P24: Oui, en cours de mise en place | Q24: Oui, déjà mis en place
A25: =A24+1 -> 22 | B25: 2 | C25: 1. Stratégie et Gouvernance | D25: AVEC/BYOD | E25: En cas d'application d'une stratégie "AVEC", quelle stratégie avez-vous mis en place pour la faire accepter par les agents ?
A26: =A25+1 -> 23 | B26: 2 | C26: 1. Stratégie et Gouvernance | D26: Mesure d'impact environnemental | E26: Quel est le niveau d’urgence de votre besoin en outils ou méthodologies de mesure ? (Faible / Moyen / élevé)
A27: =A26+1 -> 24 | B27: 2 | C27: 1. Stratégie et Gouvernance | D27: Mesure d'impact environnemental | E27: Quelles sont vos priorités ? (Se faire accompagner / Se former / Outiller / Mesurer / Suivre / etc.)
A28: =A27+1 -> 25 | B28: 1 | C28: 1. Stratégie et Gouvernance | D28: Reporting | E28: Disposez-vous d'un outil de suivi et de pilotage de la performance environnementale du SI ? | M28: Non, ne souhaite pas le faire | N28: Non, mais souhaite le faire à court terme | O28: Non, mais en cours de mise en place | P28: Oui, mais l'outil est très peu utilisé | Q28: Oui, la performance environnementale du SI est suivi et piloté à l'aide d'un outil
A29: =A28+1 -> 26 | B29: 1 | C29: 1. Stratégie et Gouvernance | D29: Sources | E29: De quelles sources proviennent les bonnes pratiques liées au Numérique Responsable mises en place par la collectivité (réglementation, organismes d'autorité, propres initiatives…)? | M29: Aucune source identifiée | N29: La collectivité applique principalement la réglementation | O29: La collectivité s'appuie sur les préconisations d'organismes reconnus comme l'ADEME, le club Green IT… | P29: La collectivité participe à des démarches exploratoires sur certains leviers | Q29: La collectivité expérimente des leviers et fait figure de précurseur
A30: =A29+1 -> 27 | B30: 1 | C30: 1. Stratégie et Gouvernance | D30: Déploiement | E30: Pourriez-vous fournir des exemples de mesures/projets/initiatives mis en place concernant le Numérique responsable ?
A31: =A30+1 -> 28 | B31: 1 | C31: 2. Mesure | D31: Empreinte environnementale du SI | E31: L'empreinte environnementale de votre SI, ou de votre projet, a-t-elle été évaluée au moins une fois ? | M31: Non | N31: Non, mais en projet | O31: Une fois | P31: Ponctuellement | Q31: Suivi régulier
A32: =A31+1 -> 29 | B32: 3 | C32: 2. Mesure | D32: Empreinte environnementale du SI | E32: Quels indicateurs sont suivis pour l'évaluation de votre empreinte environnementale du SI ?
A33: =A32+1 -> 30 | B33: 3 | C33: 2. Mesure | D33: Empreinte environnementale du SI | E33: Quels référentiels ou base de données environnementaux utilisez-vous pour faire cette évaluation ?
A34: =A33+1 -> 31 | B34: 3 | C34: 2. Mesure | D34: Empreinte environnementale du SI | E34: Avez-vous mesuré cette empreinte en interne par la collectivité ou en ayant recours à un bureau d'étude spécialisé ?
A35: =A34+1 -> 32 | B35: 3 | C35: 2. Mesure | D35: Empreinte environnementale du SI | E35: Utilisez-vous le RGESN (Référentiel général d'écoconception de services numériques) ? Le protocole GHG (protocole international proposant un cadre pour mesurer, comptabiliser et gérer les émissions de gaz à effet de serre) ? | M35: Non, ne connaît pas | N35: Non, mais connu | O35: Non, mais en cours de mise en place | P35: Oui, mais peu utilisé | Q35: Oui, utilisé
A36: =A35+1 -> 33 | B36: 1 | C36: 2. Mesure | D36: Empreinte environnementale du SI | E36: Etes-vous familier avec l'Analyse du Cycle de Vie (ACV) ? | M36: Non, ne connaît pas | N36: Non, mais connu | O36: Oui, mais peu utilisé | P36: Oui, utilisé | Q36: Oui, utilisé et maitrisé pour effectuer des calculs d'empreinte environnemental de l'IT
A37: =A36+1 -> 34 | B37: 2 | C37: 2. Mesure | D37: Empreinte environnementale du SI | E37: Si vous évaluez l'empreinte environnemental de votre SI, avez-vous une stratégie de mesure basée sur une ACV (analyse du cycle de vie) ? | M37: Non | N37: Non, mais une réflexion a été engagée | O37: Non, mais la stratégie sera mise en place à court terme | P37: Oui, les calculs sont déjà basés sur la méthodologie AVC | Q37: Oui, les calculs sont déjà basés sur la méthodologie AVC et certains agents maitrisent son utilisation
A38: =A37+1 -> 35 | B38: 2 | C38: 2. Mesure | D38: Empreinte environnementale du SI | E38: Si oui, précisez le contenu de cette stratégie avec ACV ?
A39: =A38+1 -> 36 | B39: 1 | C39: 2. Mesure | D39: Empreinte environnementale du SI | E39: Avez-vous réalisé un bilan carbone ? | M39: Non | N39: Non, mais prévu de le faire à court terme | O39: Non, mais en cours de réalisation | P39: Oui, mais incomplet et non suivi d'actions | Q39: Oui, régulièrement et inséré dans une stratégie de la CT
A40: =A39+1 -> 37 | B40: 1 | C40: 2. Mesure | D40: Empreinte environnementale du SI | E40: Publiez-vous votre BEGES (Décret bilan des émissions de gaz à effet de serre) ? | M40: Non | N40: Non, mais prévu de le faire à court terme | O40: Non, mais en cours de réalisation | P40: Oui, ponctuellement | Q40: Oui, régulièrement et inséré dans une stratégie de la CT
A41: =A40+1 -> 38 | B41: 3 | C41: 2. Mesure | D41: Empreinte environnementale du SI | E41: Evaluez-vous les émissions directes de GES (ou SCOPE 1) ? Émissions directes provenant des installations fixes ou mobiles situées à l’intérieur du périmètre organisationnel. | M41: Non | N41: Non, mais prévu de le faire à court terme | O41: Non, mais en cours de réalisation | P41: Oui, ponctuellement | Q41: Oui, régulièrement
A42: =A41+1 -> 39 | B42: 3 | C42: 2. Mesure | D42: Empreinte environnementale du SI | E42: Evaluez-vous les émissions à énergie indirectes (ou SCOPE 2) ? Émissions indirectes associées à la production d’électricité, de chaleur ou de vapeur importée pour les activités de l’organisation. | M42: Non | N42: Non, mais prévu de le faire à court terme | O42: Non, mais en cours de réalisation | P42: Oui, ponctuellement | Q42: Oui, régulièrement
A43: =A42+1 -> 40 | B43: 3 | C43: 2. Mesure | D43: Empreinte environnementale du SI | E43: Evaluez-vous les autres émissions indirectes (ou SCOPE 3) ? Les autres émissions indirectement produites par les activités de l’organisation qui ne sont pas comptabilisées au 2 mais qui sont liées à la chaîne de valeur complète comme par exemple : l’achat de matières premières, fabrication des équipements informatiques, de services ou autres produits, déplacements des salariés, transport amont et aval des marchandises, gestions des déchets générés par les activités de l’organisme, utilisation et fin de vie des produits et services vendus, immobilisation des biens et équipements de productions… | M43: Non | N43: Non, mais prévu de le faire à court terme | O43: Non, mais en cours de réalisation | P43: Oui, ponctuellement | Q43: Oui, régulièrement
A44: =A43+1 -> 41 | B44: 2 | C44: 2. Mesure | D44: Empreinte environnementale du SI | E44: Quels outils utilisez-vous pour mesurer la performance environnementale d'un service numérique (application ou site web) ?
A45: =A44+1 -> 42 | B45: 1 | C45: 3. Achat | D45: Achat d'équipements | E45: Une démarche d’achats responsables des équipements numériques est-elle mise en place ? | M45: Non | N45: Non, mais prévu de le faire à court terme | O45: Non, mais en cours de mise en place | P45: Oui, déjà mis en place pour une partie des équipements numériques | Q45: Oui, déjà mis en place pour l'ensemble des équipements numériques
A46: =A45+1 -> 43 | B46: 2 | C46: 3. Achat | D46: Achat d'équipements | E46: Publiez-vous un SPASER (Schéma de Promotion des Achats publics Socialement et Économiquement Responsables) ? (si vous êtes concerné) | M46: Non | N46: Non, mais prévu de le faire à court terme | O46: Non, mais en cours de réalisation | P46: Oui, a été publié mais n'a jamais été mis à jour | Q46: Oui, a été publié et est mis à jour régulièrement
A47: =A46+1 -> 44 | B47: 2 | C47: 3. Achat | D47: Achat d'équipements | E47: Si oui, précisez les critères environnementaux retenus et le cas échéant les questions posées sur le volet développement durable ?
A48: =A47+1 -> 45 | B48: 2 | C48: 3. Achat | D48: Achat d'équipements | E48: Communiquez-vous auprès de vos fournisseurs sur l’importance de la prise en compte des clauses environnementales et sociales dans votre phase de sourcing ? | M48: Non | N48: Non, mais c'est en cours de mise en place | O48: Oui, ponctuellement | P48: Oui, la plupart du temps | Q48: Oui, systématiquement
A49: =A48+1 -> 46 | B49: 1 | C49: 3. Achat | D49: Achat d'équipements | E49: Intégrez-vous des clauses environnementales dans vos marchés d'achat d’équipements ? | M49: Non | N49: Non, mais c'est en cours de mise en place | O49: Oui, ponctuellement | P49: Oui, la plupart du temps | Q49: Oui, systématiquement
A50: =A49+1 -> 47 | B50: 1 | C50: 3. Achat | D50: Achat d'équipements | E50: Intégrez-vous des critères environnementaux dans le choix de vos fournisseurs d’équipements numériques? | M50: Non | N50: Non, mais une réflexion a été engagée | O50: Non, mais en cours de mise en place | P50: Oui, mais le poids de ces critères n'est pas suffisamment important dans la prise de décision (représente <10% par rapport à l'ensemble des critères) | Q50: Oui, et le poids de ces critères est important (représente >10% par rapport à l'ensemble des critères)
A51: =A50+1 -> 48 | B51: 1 | C51: 3. Achat | D51: Achat d'équipements | E51: Si oui, précisez quelle est sa part dans la décision finale ? (en %)
A52: =A51+1 -> 49 | B52: 3 | C52: 3. Achat | D52: Achat d'équipements | E52: Intégrez-vous des clauses sociales dans vos marchés ? | M52: Non | N52: Non, mais c'est en cours de mise en place | O52: Oui, ponctuellement | P52: Oui, la plupart du temps | Q52: Oui, systématiquement
A53: =A52+1 -> 50 | B53: 3 | C53: 3. Achat | D53: Achat d'équipements | E53: Intégrez-vous des critères sociaux dans le choix de vos fournisseurs d’équipements numériques? | M53: Non | N53: Non, mais une réflexion a été engagée | O53: Non, mais en cours de mise en place | P53: Oui, mais le poids de ces critères n'est pas suffisamment important dans la prise de décision | Q53: Oui, et le poids de ces critères est important dans la prise de décision
A54: =A53+1 -> 51 | B54: 3 | C54: 3. Achat | D54: Achat d'équipements | E54: Si oui, précisez les critères sociaux retenus ?
A55: =A54+1 -> 52 | B55: 1 | C55: 3. Achat | D55: Achat d'équipements | E55: Dissociez-vous le renouvellement des unités centrales des autres équipements (écran, clavier, souris) ? | M55: Non | N55: Non, mais prévu de le faire à court terme | O55: Non, mais en cours de mise en place | P55: Oui, en partie | Q55: Oui, pour l'ensemble des équipements / accessoires
A56: =A55+1 -> 53 | B56: 1 | C56: 3. Achat | D56: Achat d'équipements | E56: Avez-vous un plan d'action pour réduction du nombre d'équipements par personne et par an ? | M56: Non | N56: Non, mais prévu de le faire à court terme | O56: Non, mais en cours de mise en place | P56: Oui, le plan d'action est en place pour une partie des équipements numériques | Q56: Oui, le plan d'action est en place pour l'ensemble des équipements numériques
A57: =A56+1 -> 54 | B57: 1 | C57: 3. Achat | D57: Achat d'équipements | E57: Si oui, quels équipements et quelles actions sont mis en place ?
A58: =A57+1 -> 55 | B58: 1 | C58: 3. Achat | D58: Achat d'équipements | E58: Etes vous prêts à intégrer l'indice de réparabilité des produits numériques lorsqu'ils existent dans vos marchés? | M58: Non, pas encore au clair à ce sujet | N58: Non, mais le sujet a été étudié | O58: Non, mais en cours de mise en place | P58: Oui, prêt pour tout renouvellement marché à partir de 2023 | Q58: Oui, c'est déjà intégré dans les marchés
A59: =A58+1 -> 56 | B59: 1 | C59: 3. Achat | D59: Achat d'équipements d'occasion ou reconditionné | E59: Quelle est la part de l'achat de matériel informatique d'occasion ou reconditionné par rapport à l'achat de neuf ? (en %) | M59: <10% | N59: >10% et <20% | O59: >20% et <30% | P59: >30% et <40% | Q59: >40%
A60: =A59+1 -> 57 | B60: 1 | C60: 3. Achat | D60: Achat d'équipements d'occasion ou reconditionné | E60: Si oui, pouvez-vous nous décrire les équipements concernés et les revendeurs retenus ?
A61: =A60+1 -> 58 | B61: 2 | C61: 3. Achat | D61: Achat d'équipements d'occasion ou reconditionné | E61: Avez-vous des fournisseurs qui proposent des copieurs reconditionnés ? | M61: Non | N61: Non, mais souhaite les identifier | O61: Non, mais en cours d'identification des fournisseurs | P61: Oui, en cours de mise en relation avec un/des fournisseurs | Q61: Oui
A62: =A61+1 -> 59 | B62: 2 | C62: 3. Achat | D62: Achat d'équipements d'occasion ou reconditionné | E62: Si oui, quels sont les fournisseurs retenus ?
A63: =A62+1 -> 60 | B63: 3 | C63: 3. Achat | D63: Achat d'équipements d'occasion ou reconditionné | E63: Quelle part de vos copieurs est issue d'une filière de reconditionnement ? (en %) | M63: <10% | N63: >10% et <20% | O63: >20% et <30% | P63: >30% et <40% | Q63: >40%
A64: =A63+1 -> 61 | B64: 3 | C64: 3. Achat | D64: Achat d'équipements d'occasion ou reconditionné | E64: Quelle est la part des cartouches d'impression issue d'une filière de reconditionnement ? (en %) | M64: <10% | N64: >10% et <20% | O64: >20% et <30% | P64: >30% et <40% | Q64: >40%
A65: =A64+1 -> 62 | B65: 2 | C65: 3. Achat | D65: Achat d'équipements d'occasion ou reconditionné | E65: Comment anticipez-vous les nouvelles réglementations sur le sujet (exemple la loi relative à la lutte contre le gaspillage et à l'économie circulaire) ?
A66: =A65+1 -> 63 | B66: 1 | C66: 3. Achat | D66: Location | E66: Avez-vous mis en place une stratégie de location de matériels plutôt que d'achat ? | M66: Non | N66: Non, mais une réflexion a été engagée | O66: Oui, pour une petite partie des équipements de la collectivité | P66: Oui, pour une grande partie des équipements de la collectivité | Q66: Oui, pour quasiment l'ensemble des équipements de la collectivité
A67: =A66+1 -> 64 | B67: 2 | C67: 3. Achat | D67: Location | E67: Pouvez-vous nous décrire les équipements concernés par la location, le % par rapport au parc global et les fournisseurs retenus ?
A68: =A67+1 -> 65 | B68: 3 | C68: 3. Achat | D68: Achat de services | E68: Intégrez-vous des clauses environnementales et sociales dans vos appels d’offres de services et prestations intellectuelles ? | M68: Non | N68: Non, mais c'est en cours de mise en place | O68: Oui, ponctuellement | P68: Oui, la plupart du temps | Q68: Oui, systématiquement
A69: =A68+1 -> 66 | B69: 3 | C69: 3. Achat | D69: Achat de services | E69: Pouvez vous lister des exemples de clauses environnementales et sociales qui, d'après vous, ont le plus de poids environnemental ?
A70: =A69+1 -> 67 | B70: 2 | C70: 3. Achat | D70: Achat de services | E70: Choisissez-vous un prestataire d'hébergement ou opérateurs datacenters selon des critères de performance environnementale ? | M70: Non | N70: Non, mais prévu de le faire à court terme | O70: Non, mais en cours de mise en place | P70: Oui, mais le poids de ces critères n'est pas suffisamment important dans la prise de décision | Q70: Oui, et le poids de ces critères est important dans la prise de décision
A71: =A70+1 -> 68 | B71: 2 | C71: 3. Achat | D71: Achat de services | E71: Si oui, quelles sont les critères retenus ?
A72: =A71+1 -> 69 | B72: 1 | C72: 3. Achat | D72: Achat de services | E72: Quel est la proportion des projets numériques démarrés en 2022 qui intègrent des clauses environnementales et sociales ? | M72: <10% | N72: 10%<X<30% | O72: 30%<X<50% | P72: 50%<X<70% | Q72: >70%
A73: =A72+1 -> 70 | B73: 1 | C73: 3. Achat | D73: Achat de services | E73: Depuis quand ces clauses existent ?
A74: =A73+1 -> 71 | B74: 2 | C74: 3. Achat | D74: Achat de services | E74: Est-ce que le fait d'intégrer ces clauses font partie d'une politique/stratégie clairement définie ? | M74: Non | N74: Non, mais une réflexion a été engagée | O74: Non, mais sera mis en place à court terme | P74: Non, mais en cours de mise en place | Q74: Oui, c'est clairement défini dans la politique/stratégie de la collectivité
A75: =A74+1 -> 72 | B75: 1 | C75: 3. Achat | D75: Achat de services | E75: Pouvez-vous nous communiquer un exemple de CCTP (Cahier des Clauses Techniques Particulières) intégrant des clauses environnementales et sociales ?
A76: =A75+1 -> 73 | B76: 2 | C76: 3. Achat | D76: Achat d'énergie | E76: Achetez-vous de l’énergie renouvelable pour alimenter le système d’information ? | M76: Non | N76: Non, mais une réflexion a été engagée | O76: Non, mais en cours de mise en place | P76: Oui, une partie du SI est déjà alimentée par de l'énergie renouvelable | Q76: Oui, la quasi-totalité du SI est alimentée par de l'énergie renouvelable
A77: =A76+1 -> 74 | B77: 2 | C77: 3. Achat | D77: Achat d'énergie | E77: Si oui, quel opérateur et quelle offre sont retenus ?
A78: =A77+1 -> 75 | B78: 2 | C78: 3. Achat | D78: Labels | E78: Quelle est la part de l'achat d'équipements (ordinateurs, téléphonie) éco-labellisés par rapport au total ? (en %) | M78: <10% | N78: 10%<X<30% | O78: 30%<X<50% | P78: 50%<X<70% | Q78: >70%
A79: =A78+1 -> 76 | B79: 2 | C79: 3. Achat | D79: Labels | E79: Si oui, quels labels avez-vous identifié et pourquoi ?
A80: =A79+1 -> 77 | B80: 2 | C80: 3. Achat | D80: Labels | E80: Envisagez-vous en 2023 d'engager votre organisation dans une labellisation concernant la réduction de l'impact du numérique ? | M80: Non | N80: Non, mais une réflexion a été engagée | O80: Non, mais en cours de mise en place | P80: Oui, le processus de certification est en cours | Q80: Oui, nous sommes labellisés
A81: =A80+1 -> 78 | B81: 2 | C81: 3. Achat | D81: Labels | E81: Si oui, laquelle ?
A82: =A81+1 -> 79 | B82: 1 | C82: 4. Transformation de l'IT | D82: Conception | E82: Mettez-vous en œuvre des bonnes pratiques de conception de services numériques ? | M82: Non | N82: Non, mais une petite partie des agents concernés est sensibilisée | O82: Non, mais une grande partie des agents concernés est sensibilisée | P82: Oui, pratiqué par certains agents concernés | Q82: Oui, pratiqué par l'ensemble des agents concernés
A83: =A82+1 -> 80 | B83: 1 | C83: 4. Transformation de l'IT | D83: Conception | E83: Quelles sont vos bonnes pratiques de conception de services numériques ?
A84: =A83+1 -> 81 | B84: 2 | C84: 4. Transformation de l'IT | D84: Conception | E84: Vos bonnes pratiques de conception de services numériques sont-elles liées à l'éco-conception de services numériques ?
A85: =A84+1 -> 82 | B85: 2 | C85: 4. Transformation de l'IT | D85: Conception | E85: Si oui, quels référentiels ou bonnes pratiques utilisez-vous ?
A86: =A85+1 -> 83 | B86: 1 | C86: 4. Transformation de l'IT | D86: Conception | E86: Une stratégie de gestion des données (durée de conservation et volume stocké) est-elle mise en place ? | M86: Non | N86: Non, mais une réflexion a été engagée | O86: Non, mais en cours de mise en place | P86: Oui, une stratégie est mise en place pour certains aspects | Q86: Oui, une stratégie est mise en place pour l'ensemble des aspects
A87: =A86+1 -> 84 | B87: 3 | C87: 4. Transformation de l'IT | D87: Conception | E87: Avez-vous travaillé sur la réduction du temps passé par un agent ou un usager sur vos services numériques (le temps moyen pour obtenir une information ou faire une démarche) ? | M87: Non | N87: Non, mais une réflexion a été engagée | O87: Non, mais en cours de mise en place | P87: Oui, pour une partie de nos services numériques | Q87: Oui, pour quasiment l'ensemble de nos services numériques
A88: =A87+1 -> 85 | B88: 3 | C88: 4. Transformation de l'IT | D88: Conception | E88: Si oui, comment ?
A89: =A88+1 -> 86 | B89: 1 | C89: 4. Transformation de l'IT | D89: Conception | E89: Quelle est la part de solutions open-source dans vos projets ? (en %) | M89: <10% | N89: 10%<X<30% | O89: 30%<X<50% | P89: 50%<X<70% | Q89: >70%
A90: =A89+1 -> 87 | B90: 3 | C90: 4. Transformation de l'IT | D90: Conception | E90: Si vous en avez la responsabilité, concevez-vous une charte graphique responsable ? | M90: Non et ne souhaite pas le faire | N90: Non, mais souhaite le faire à court terme | O90: Non, mais c'est en cours | P90: Oui, existante | Q90: Oui, existante et a été communiquée au sein de la collectivité
A91: =A90+1 -> 88 | B91: 3 | C91: 4. Transformation de l'IT | D91: Conception | E91: Si oui, avez-vous des exemples de points d'attention lors de la conception de charte graphique responsable ?
A92: =A91+1 -> 89 | B92: 1 | C92: 4. Transformation de l'IT | D92: Conception | E92: Mobilisez-vous un chef de produit, un ou plusieurs designers UX, un expert accessibilité, et un chercheur usager sur la conception de vos services numériques ? | M92: Non, pas du tout | N92: Ponctuellement et pour uniquement certains des rôles mentionnés | O92: Souvent et pour la plupart des rôles mentionnés | P92: Généralisé mais pour uniquement certains des rôles mentionnés | Q92: Généralisé pour l'ensemble des rôles mentionnés
A93: =A92+1 -> 90 | B93: 2 | C93: 4. Transformation de l'IT | D93: Conception | E93: Avez-vous besoin d'un chef de produit, expert accessibilité, designer UX ou chercheur usager ?
A94: =A93+1 -> 91 | B94: 2 | C94: 4. Transformation de l'IT | D94: Conception | E94: Le RGAA (Référentiel général d'amélioration de l'accessibilité) est-il mis en œuvre lors du développement interne d'une application ? | M94: Non | N94: Non, mais entendu parlé | O94: Non, mais connait bien ce référentiel | P94: Oui, appliqué de manière ponctuelle | Q94: Oui, appliqué de manière systématique
A95: =A94+1 -> 92 | B95: 2 | C95: 4. Transformation de l'IT | D95: Conception | E95: Si oui, avez-vous des exemples de bonnes pratiques mises en place ou un projet exemplaire lié à la mise en œuvre du RGAA ?
A96: =A95+1 -> 93 | B96: 2 | C96: 4. Transformation de l'IT | D96: Conception | E96: Le RGAA est-il systématiquement pris en compte par les éditeurs de logiciel ? | M96: Non, pas du tout | N96: Non, mais en cours de mise en place | O96: Oui, ponctuellement | P96: Oui, régulièrement | Q96: Oui, systématiquement
A97: =A96+1 -> 94 | B97: 2 | C97: 4. Transformation de l'IT | D97: Conception | E97: La conformité au RGPD est-elle systématiquement mise en place lors du développement interne d'une application ? | M97: Non, pas du tout | N97: Non, mais en cours de mise en place | O97: Oui, ponctuellement | P97: Oui, régulièrement | Q97: Oui, systématiquement
A98: =A97+1 -> 95 | B98: 2 | C98: 4. Transformation de l'IT | D98: Conception | E98: Si oui, comment ?
A99: =A98+1 -> 96 | B99: 2 | C99: 4. Transformation de l'IT | D99: Conception | E99: La conformité au RGPD est-elle systématiquement mise en place par les éditeurs de logiciel ? | M99: Non, pas du tout | N99: Non, mais en cours de mise en place | O99: Oui, ponctuellement | P99: Oui, régulièrement | Q99: Oui, systématiquement
A100: =A99+1 -> 97 | B100: 3 | C100: 4. Transformation de l'IT | D100: Méthodes de conception | E100: Quelle méthode de développement de logiciel utilisez-vous ? (Cycle en V, Scrum, Safe…)
...

Sheet 2. Note de maturité
B1: Calcul des notes par question | I1: Calcul des notes par dimension | N1: Note de maturité par dimension
B3: N° | C3: Note 1 | D3: Note 2 | E3: Note moyenne | F3: Pondération | G3: Note pondérée | I3: Dimension | J3: Somme note pondérée | K3: Somme pondération | L3: Note pondérée | N3: Dimension | O3: Note de maturité
B4: 1 | C4: =IF('1. Questionnaire d''entretien '!R4="","N/A",'1. Questionnaire d''entretien '!R4) -> N/A | D4: =IF('1. Questionnaire d''entretien '!T4="","N/A",'1. Questionnaire d''entretien '!T4) -> N/A | E4: =IF(AND(C4="N/A",D4="N/A"),"N/A",AVERAGE(C4:D4)) -> N/A | F4: {=_xlfn.IFS('1. Questionnaire d''entretien '!B4=1,1,'1. Questionnaire d''entretien '!B4=2,0.75,'1. Questionnaire d''entretien '!B4=3,0.5)} -> 1 | G4: =IF(E4="N/A","N/A",E4*F4) -> N/A | I4: 1. Stratégie et Gouvernance | J4: =SUMIF('1. Questionnaire d''entretien '!$C$4:$C$215,I4,'2. Note de maturité'!$G$4:$G$215) -> 0 | K4: =SUMIFS($F$4:$F$215,'1. Questionnaire d''entretien '!$C$4:$C$215,'2. Note de maturité'!I4,'2. Note de maturité'!$E$4:$E$215,"<>N/A") -> 0 | L4: =J4/K4 -> #DIV/0! | N4: 1. Stratégie et Gouvernance | O4: =IF(ISNUMBER(L4),L4,"N/A") -> N/A
B5: =B4+1 -> 2 | C5: =IF('1. Questionnaire d''entretien '!R5="","N/A",'1. Questionnaire d''entretien '!R5) -> N/A | D5: =IF('1. Questionnaire d''entretien '!T5="","N/A",'1. Questionnaire d''entretien '!T5) -> N/A | E5: =IF(AND(C5="N/A",D5="N/A"),"N/A",AVERAGE(C5:D5)) -> N/A | F5: {=_xlfn.IFS('1. Questionnaire d''entretien '!B5=1,1,'1. Questionnaire d''entretien '!B5=2,0.75,'1. Questionnaire d''entretien '!B5=3,0.5)} -> 1 | G5: =IF(E5="N/A","N/A",E5*F5) -> N/A | I5: 2. Mesure | J5: =SUMIF('1. Questionnaire d''entretien '!$C$4:$C$215,I5,'2. Note de maturité'!$G$4:$G$215) -> 0 | K5: =SUMIFS($F$4:$F$215,'1. Questionnaire d''entretien '!$C$4:$C$215,'2. Note de maturité'!I5,'2. Note de maturité'!$E$4:$E$215,"<>N/A") -> 0 | L5: =J5/K5 -> #DIV/0! | N5: 2. Mesure | O5: =IF(ISNUMBER(L5),L5,"N/A") -> N/A
B6: =B5+1 -> 3 | C6: =IF('1. Questionnaire d''entretien '!R6="","N/A",'1. Questionnaire d''entretien '!R6) -> N/A | D6: =IF('1. Questionnaire d''entretien '!T6="","N/A",'1. Questionnaire d''entretien '!T6) -> N/A | E6: =IF(AND(C6="N/A",D6="N/A"),"N/A",AVERAGE(C6:D6)) -> N/A | F6: {=_xlfn.IFS('1. Questionnaire d''entretien '!B6=1,1,'1. Questionnaire d''entretien '!B6=2,0.75,'1. Questionnaire d''entretien '!B6=3,0.5)} -> 1 | G6: =IF(E6="N/A","N/A",E6*F6) -> N/A | I6: 3. Achat | J6: =SUMIF('1. Questionnaire d''entretien '!$C$4:$C$215,I6,'2. Note de maturité'!$G$4:$G$215) -> 0 | K6: =SUMIFS($F$4:$F$215,'1. Questionnaire d''entretien '!$C$4:$C$215,'2. Note de maturité'!I6,'2. Note de maturité'!$E$4:$E$215,"<>N/A") -> 0 | L6: =J6/K6 -> #DIV/0! | N6: 3. Achat | O6: =IF(ISNUMBER(L6),L6,"N/A") -> N/A
B7: =B6+1 -> 4 | C7: =IF('1. Questionnaire d''entretien '!R7="","N/A",'1. Questionnaire d''entretien '!R7) -> N/A | D7: =IF('1. Questionnaire d''entretien '!T7="","N/A",'1. Questionnaire d''entretien '!T7) -> N/A | E7: =IF(AND(C7="N/A",D7="N/A"),"N/A",AVERAGE(C7:D7)) -> N/A | F7: {=_xlfn.IFS('1. Questionnaire d''entretien '!B7=1,1,'1. Questionnaire d''entretien '!B7=2,0.75,'1. Questionnaire d''entretien '!B7=3,0.5)} -> 1 | G7: =IF(E7="N/A","N/A",E7*F7) -> N/A | I7: 4. Transformation de l'IT | J7: =SUMIF('1. Questionnaire d''entretien '!$C$4:$C$215,I7,'2. Note de maturité'!$G$4:$G$215) -> 0 | K7: =SUMIFS($F$4:$F$215,'1. Questionnaire d''entretien '!$C$4:$C$215,'2. Note de maturité'!I7,'2. Note de maturité'!$E$4:$E$215,"<>N/A") -> 0 | L7: =J7/K7 -> #DIV/0! | N7: 4. Transformation de l'IT | O7: =IF(ISNUMBER(L7),L7,"N/A") -> N/A
B8: =B7+1 -> 5 | C8: =IF('1. Questionnaire d''entretien '!R8="","N/A",'1. Questionnaire d''entretien '!R8) -> N/A | D8: =IF('1. Questionnaire d''entretien '!T8="","N/A",'1. Questionnaire d''entretien '!T8) -> N/A | E8: =IF(AND(C8="N/A",D8="N/A"),"N/A",AVERAGE(C8:D8)) -> N/A | F8: {=_xlfn.IFS('1. Questionnaire d''entretien '!B8=1,1,'1. Questionnaire d''entretien '!B8=2,0.75,'1. Questionnaire d''entretien '!B8=3,0.5)} -> 0.75 | G8: =IF(E8="N/A","N/A",E8*F8) -> N/A | I8: 5. DEEE et Economie circulaire | J8: =SUMIF('1. Questionnaire d''entretien '!$C$4:$C$215,I8,'2. Note de maturité'!$G$4:$G$215) -> 0 | K8: =SUMIFS($F$4:$F$215,'1. Questionnaire d''entretien '!$C$4:$C$215,'2. Note de maturité'!I8,'2. Note de maturité'!$E$4:$E$215,"<>N/A") -> 0 | L8: =J8/K8 -> #DIV/0! | N8: 5. DEEE et Economie circulaire | O8: =IF(ISNUMBER(L8),L8,"N/A") -> N/A
B9: =B8+1 -> 6 | C9: =IF('1. Questionnaire d''entretien '!R9="","N/A",'1. Questionnaire d''entretien '!R9) -> N/A | D9: =IF('1. Questionnaire d''entretien '!T9="","N/A",'1. Questionnaire d''entretien '!T9) -> N/A | E9: =IF(AND(C9="N/A",D9="N/A"),"N/A",AVERAGE(C9:D9)) -> N/A | F9: {=_xlfn.IFS('1. Questionnaire d''entretien '!B9=1,1,'1. Questionnaire d''entretien '!B9=2,0.75,'1. Questionnaire d''entretien '!B9=3,0.5)} -> 1 | G9: =IF(E9="N/A","N/A",E9*F9) -> N/A | I9: 6. Sensibilisation | J9: =SUMIF('1. Questionnaire d''entretien '!$C$4:$C$215,I9,'2. Note de maturité'!$G$4:$G$215) -> 0 | K9: =SUMIFS($F$4:$F$215,'1. Questionnaire d''entretien '!$C$4:$C$215,'2. Note de maturité'!I9,'2. Note de maturité'!$E$4:$E$215,"<>N/A") -> 0 | L9: =J9/K9 -> #DIV/0! | N9: 6. Sensibilisation | O9: =IF(ISNUMBER(L9),L9,"N/A") -> N/A
B10: =B9+1 -> 7 | C10: =IF('1. Questionnaire d''entretien '!R10="","N/A",'1. Questionnaire d''entretien '!R10) -> N/A | D10: =IF('1. Questionnaire d''entretien '!T10="","N/A",'1. Questionnaire d''entretien '!T10) -> N/A | E10: =IF(AND(C10="N/A",D10="N/A"),"N/A",AVERAGE(C10:D10)) -> N/A | F10: {=_xlfn.IFS('1. Questionnaire d''entretien '!B10=1,1,'1. Questionnaire d''entretien '!B10=2,0.75,'1. Questionnaire d''entretien '!B10=3,0.5)} -> 1 | G10: =IF(E10="N/A","N/A",E10*F10) -> N/A | I10: 7. IT pour une Collectivité Eco-responsable | J10: =SUMIF('1. Questionnaire d''entretien '!$C$4:$C$215,I10,'2. Note de maturité'!$G$4:$G$215) -> 0 | K10: =SUMIFS($F$4:$F$215,'1. Questionnaire d''entretien '!$C$4:$C$215,'2. Note de maturité'!I10,'2. Note de maturité'!$E$4:$E$215,"<>N/A") -> 0 | L10: =J10/K10 -> #DIV/0! | N10: 7. IT pour une Collectivité Eco-responsable | O10: =IF(ISNUMBER(L10),L10,"N/A") -> N/A
B11: =B10+1 -> 8 | C11: =IF('1. Questionnaire d''entretien '!R11="","N/A",'1. Questionnaire d''entretien '!R11) -> N/A | D11: =IF('1. Questionnaire d''entretien '!T11="","N/A",'1. Questionnaire d''entretien '!T11) -> N/A | E11: =IF(AND(C11="N/A",D11="N/A"),"N/A",AVERAGE(C11:D11)) -> N/A | F11: {=_xlfn.IFS('1. Questionnaire d''entretien '!B11=1,1,'1. Questionnaire d''entretien '!B11=2,0.75,'1. Questionnaire d''entretien '!B11=3,0.5)} -> 1 | G11: =IF(E11="N/A","N/A",E11*F11) -> N/A
B12: =B11+1 -> 9 | C12: =IF('1. Questionnaire d''entretien '!R12="","N/A",'1. Questionnaire d''entretien '!R12) -> N/A | D12: =IF('1. Questionnaire d''entretien '!T12="","N/A",'1. Questionnaire d''entretien '!T12) -> N/A | E12: =IF(AND(C12="N/A",D12="N/A"),"N/A",AVERAGE(C12:D12)) -> N/A | F12: {=_xlfn.IFS('1. Questionnaire d''entretien '!B12=1,1,'1. Questionnaire d''entretien '!B12=2,0.75,'1. Questionnaire d''entretien '!B12=3,0.5)} -> 0.75 | G12: =IF(E12="N/A","N/A",E12*F12) -> N/A
B13: =B12+1 -> 10 | C13: =IF('1. Questionnaire d''entretien '!R13="","N/A",'1. Questionnaire d''entretien '!R13) -> N/A | D13: =IF('1. Questionnaire d''entretien '!T13="","N/A",'1. Questionnaire d''entretien '!T13) -> N/A | E13: =IF(AND(C13="N/A",D13="N/A"),"N/A",AVERAGE(C13:D13)) -> N/A | F13: {=_xlfn.IFS('1. Questionnaire d''entretien '!B13=1,1,'1. Questionnaire d''entretien '!B13=2,0.75,'1. Questionnaire d''entretien '!B13=3,0.5)} -> 0.5 | G13: =IF(E13="N/A","N/A",E13*F13) -> N/A | N13: Note de maturité globale
B14: =B13+1 -> 11 | C14: =IF('1. Questionnaire d''entretien '!R14="","N/A",'1. Questionnaire d''entretien '!R14) -> N/A | D14: =IF('1. Questionnaire d''entretien '!T14="","N/A",'1. Questionnaire d''entretien '!T14) -> N/A | E14: =IF(AND(C14="N/A",D14="N/A"),"N/A",AVERAGE(C14:D14)) -> N/A | F14: {=_xlfn.IFS('1. Questionnaire d''entretien '!B14=1,1,'1. Questionnaire d''entretien '!B14=2,0.75,'1. Questionnaire d''entretien '!B14=3,0.5)} -> 0.5 | G14: =IF(E14="N/A","N/A",E14*F14) -> N/A
B15: =B14+1 -> 12 | C15: =IF('1. Questionnaire d''entretien '!R15="","N/A",'1. Questionnaire d''entretien '!R15) -> N/A | D15: =IF('1. Questionnaire d''entretien '!T15="","N/A",'1. Questionnaire d''entretien '!T15) -> N/A | E15: =IF(AND(C15="N/A",D15="N/A"),"N/A",AVERAGE(C15:D15)) -> N/A | F15: {=_xlfn.IFS('1. Questionnaire d''entretien '!B15=1,1,'1. Questionnaire d''entretien '!B15=2,0.75,'1. Questionnaire d''entretien '!B15=3,0.5)} -> 0.75 | G15: =IF(E15="N/A","N/A",E15*F15) -> N/A | N15: =AVERAGE(O4:O10) -> #DIV/0!
B16: =B15+1 -> 13 | C16: =IF('1. Questionnaire d''entretien '!R16="","N/A",'1. Questionnaire d''entretien '!R16) -> N/A | D16: =IF('1. Questionnaire d''entretien '!T16="","N/A",'1. Questionnaire d''entretien '!T16) -> N/A | E16: =IF(AND(C16="N/A",D16="N/A"),"N/A",AVERAGE(C16:D16)) -> N/A | F16: {=_xlfn.IFS('1. Questionnaire d''entretien '!B16=1,1,'1. Questionnaire d''entretien '!B16=2,0.75,'1. Questionnaire d''entretien '!B16=3,0.5)} -> 0.75 | G16: =IF(E16="N/A","N/A",E16*F16) -> N/A
B17: =B16+1 -> 14 | C17: =IF('1. Questionnaire d''entretien '!R17="","N/A",'1. Questionnaire d''entretien '!R17) -> N/A | D17: =IF('1. Questionnaire d''entretien '!T17="","N/A",'1. Questionnaire d''entretien '!T17) -> N/A | E17: =IF(AND(C17="N/A",D17="N/A"),"N/A",AVERAGE(C17:D17)) -> N/A | F17: {=_xlfn.IFS('1. Questionnaire d''entretien '!B17=1,1,'1. Questionnaire d''entretien '!B17=2,0.75,'1. Questionnaire d''entretien '!B17=3,0.5)} -> 1 | G17: =IF(E17="N/A","N/A",E17*F17) -> N/A
B18: =B17+1 -> 15 | C18: =IF('1. Questionnaire d''entretien '!R18="","N/A",'1. Questionnaire d''entretien '!R18) -> N/A | D18: =IF('1. Questionnaire d''entretien '!T18="","N/A",'1. Questionnaire d''entretien '!T18) -> N/A | E18: =IF(AND(C18="N/A",D18="N/A"),"N/A",AVERAGE(C18:D18)) -> N/A | F18: {=_xlfn.IFS('1. Questionnaire d''entretien '!B18=1,1,'1. Questionnaire d''entretien '!B18=2,0.75,'1. Questionnaire d''entretien '!B18=3,0.5)} -> 1 | G18: =IF(E18="N/A","N/A",E18*F18) -> N/A
B19: =B18+1 -> 16 | C19: =IF('1. Questionnaire d''entretien '!R19="","N/A",'1. Questionnaire d''entretien '!R19) -> N/A | D19: =IF('1. Questionnaire d''entretien '!T19="","N/A",'1. Questionnaire d''entretien '!T19) -> N/A | E19: =IF(AND(C19="N/A",D19="N/A"),"N/A",AVERAGE(C19:D19)) -> N/A | F19: {=_xlfn.IFS('1. Questionnaire d''entretien '!B19=1,1,'1. Questionnaire d''entretien '!B19=2,0.75,'1. Questionnaire d''entretien '!B19=3,0.5)} -> 0.75 | G19: =IF(E19="N/A","N/A",E19*F19) -> N/A
B20: =B19+1 -> 17 | C20: =IF('1. Questionnaire d''entretien '!R20="","N/A",'1. Questionnaire d''entretien '!R20) -> N/A | D20: =IF('1. Questionnaire d''entretien '!T20="","N/A",'1. Questionnaire d''entretien '!T20) -> N/A | E20: =IF(AND(C20="N/A",D20="N/A"),"N/A",AVERAGE(C20:D20)) -> N/A | F20: {=_xlfn.IFS('1. Questionnaire d''entretien '!B20=1,1,'1. Questionnaire d''entretien '!B20=2,0.75,'1. Questionnaire d''entretien '!B20=3,0.5)} -> 0.75 | G20: =IF(E20="N/A","N/A",E20*F20) -> N/A
B21: =B20+1 -> 18 | C21: =IF('1. Questionnaire d''entretien '!R21="","N/A",'1. Questionnaire d''entretien '!R21) -> N/A | D21: =IF('1. Questionnaire d''entretien '!T21="","N/A",'1. Questionnaire d''entretien '!T21) -> N/A | E21: =IF(AND(C21="N/A",D21="N/A"),"N/A",AVERAGE(C21:D21)) -> N/A | F21: {=_xlfn.IFS('1. Questionnaire d''entretien '!B21=1,1,'1. Questionnaire d''entretien '!B21=2,0.75,'1. Questionnaire d''entretien '!B21=3,0.5)} -> 0.75 | G21: =IF(E21="N/A","N/A",E21*F21) -> N/A
B22: =B21+1 -> 19 | C22: =IF('1. Questionnaire d''entretien '!R22="","N/A",'1. Questionnaire d''entretien '!R22) -> N/A | D22: =IF('1. Questionnaire d''entretien '!T22="","N/A",'1. Questionnaire d''entretien '!T22) -> N/A | E22: =IF(AND(C22="N/A",D22="N/A"),"N/A",AVERAGE(C22:D22)) -> N/A | F22: {=_xlfn.IFS('1. Questionnaire d''entretien '!B22=1,1,'1. Questionnaire d''entretien '!B22=2,0.75,'1. Questionnaire d''entretien '!B22=3,0.5)} -> 0.5 | G22: =IF(E22="N/A","N/A",E22*F22) -> N/A
B23: =B22+1 -> 20 | C23: =IF('1. Questionnaire d''entretien '!R23="","N/A",'1. Questionnaire d''entretien '!R23) -> N/A | D23: =IF('1. Questionnaire d''entretien '!T23="","N/A",'1. Questionnaire d''entretien '!T23) -> N/A | E23: =IF(AND(C23="N/A",D23="N/A"),"N/A",AVERAGE(C23:D23)) -> N/A | F23: {=_xlfn.IFS('1. Questionnaire d''entretien '!B23=1,1,'1. Questionnaire d''entretien '!B23=2,0.75,'1. Questionnaire d''entretien '!B23=3,0.5)} -> 0.75 | G23: =IF(E23="N/A","N/A",E23*F23) -> N/A
B24: =B23+1 -> 21 | C24: =IF('1. Questionnaire d''entretien '!R24="","N/A",'1. Questionnaire d''entretien '!R24) -> N/A | D24: =IF('1. Questionnaire d''entretien '!T24="","N/A",'1. Questionnaire d''entretien '!T24) -> N/A | E24: =IF(AND(C24="N/A",D24="N/A"),"N/A",AVERAGE(C24:D24)) -> N/A | F24: {=_xlfn.IFS('1. Questionnaire d''entretien '!B24=1,1,'1. Questionnaire d''entretien '!B24=2,0.75,'1. Questionnaire d''entretien '!B24=3,0.5)} -> 0.75 | G24: =IF(E24="N/A","N/A",E24*F24) -> N/A
B25: =B24+1 -> 22 | C25: =IF('1. Questionnaire d''entretien '!R25="","N/A",'1. Questionnaire d''entretien '!R25) -> N/A | D25: =IF('1. Questionnaire d''entretien '!T25="","N/A",'1. Questionnaire d''entretien '!T25) -> N/A | E25: =IF(AND(C25="N/A",D25="N/A"),"N/A",AVERAGE(C25:D25)) -> N/A | F25: {=_xlfn.IFS('1. Questionnaire d''entretien '!B25=1,1,'1. Questionnaire d''entretien '!B25=2,0.75,'1. Questionnaire d''entretien '!B25=3,0.5)} -> 0.75 | G25: =IF(E25="N/A","N/A",E25*F25) -> N/A
B26: =B25+1 -> 23 | C26: =IF('1. Questionnaire d''entretien '!R26="","N/A",'1. Questionnaire d''entretien '!R26) -> N/A | D26: =IF('1. Questionnaire d''entretien '!T26="","N/A",'1. Questionnaire d''entretien '!T26) -> N/A | E26: =IF(AND(C26="N/A",D26="N/A"),"N/A",AVERAGE(C26:D26)) -> N/A | F26: {=_xlfn.IFS('1. Questionnaire d''entretien '!B26=1,1,'1. Questionnaire d''entretien '!B26=2,0.75,'1. Questionnaire d''entretien '!B26=3,0.5)} -> 0.75 | G26: =IF(E26="N/A","N/A",E26*F26) -> N/A
B27: =B26+1 -> 24 | C27: =IF('1. Questionnaire d''entretien '!R27="","N/A",'1. Questionnaire d''entretien '!R27) -> N/A | D27: =IF('1. Questionnaire d''entretien '!T27="","N/A",'1. Questionnaire d''entretien '!T27) -> N/A | E27: =IF(AND(C27="N/A",D27="N/A"),"N/A",AVERAGE(C27:D27)) -> N/A | F27: {=_xlfn.IFS('1. Questionnaire d''entretien '!B27=1,1,'1. Questionnaire d''entretien '!B27=2,0.75,'1. Questionnaire d''entretien '!B27=3,0.5)} -> 0.75 | G27: =IF(E27="N/A","N/A",E27*F27) -> N/A
... B215: =B214+1 -> 212 | C215: =IF('1. Questionnaire d''entretien '!R215="","N/A",'1. Questionnaire d''entretien '!R215) -> N/A | D215: =IF('1. Questionnaire d''entretien '!T215="","N/A",'1. Questionnaire d''entretien '!T215) -> N/A | E215: =IF(AND(C215="N/A",D215="N/A"),"N/A",AVERAGE(C215:D215)) -> N/A | F215: {=_xlfn.IFS('1. Questionnaire d''entretien '!B215=1,1,'1. Questionnaire d''entretien '!B215=2,0.75,'1. Questionnaire d''entretien '!B215=3,0.5)} -> 0.75 | G215: =IF(E215="N/A","N/A",E215*F215) -> N/A

Sheet 3. Glossaire
A1: Acronyme | B1: Signification
A2: ACV | B2: Analyse de Cycle de Vie
A3: AR | B3: Réalité Augmentée
A4: AVEC/BYOD | B4: Apportez Votre Equipement personnel de Communication/Bring Your Own Device
A5: CCTP | B5: Cahier des Clauses Techniques Particulières
A6: DEEE | B6: Déchets d’Equipements Electriques et Electroniques
A7: DINUM | B7: Direction interministérielle du numérique
A8: GES | B8: Gas à Effet de Serre
A9: IA | B9: Intelligence Artificielle
A10: INR | B10: Institut du Numérique Responsable
A11: IT | B11: Information Technology (Technologies de l'information)
A12: NR | B12: Numérique Responsable
... A18: VR | B18: Réalité Virtuelle

Sheet Validation des données
B2: Note
B3: 0
B4: 1
B5: 2
B6: 3
B7: 4
B8: N/A

Sheet 1. Stratégie et Gouvernance
A1: Grille d'entretien | G1: Grille de notation
A2: Niveau | B2: Pilier | C2: Thématique | D2: Question | E2: Types de réponses | F2: Acteur répondant | G2: 1 | H2: 2 | I2: 3 | J2: 4
A3: 1 | B3: 1. Stratégie et Gouvernance | C3: Stratégie globale | D3: L'engagement environnemental et sociétal fait-il partie des valeurs de la collectivité ? | G3: Non | H3: Il s'agit d'un centre d'intérêt des agents mais pas d'une valeur de la collectivité | I3: C'est une valeur secondaire de la collectivité | J3: C'est une valeur principale de la collectivité
A4: 1 | B4: 1. Stratégie et Gouvernance | C4: Stratégie NR | D4: Avez-vous déjà intégré une dimension écologique à la gestion du numérique dans votre organisation ? | G4: Non | H4: Des initiatives indépendantes/non coordonnées ont été lancées au sein de la DSI seulement | I4: Plusieurs initiatives existent et une démarche globale est en cours de définition/lancement | J4: Une démarche stratégique globale a été lancée et a atteint de premiers objectifs
A5: 1 | B5: 1. Stratégie et Gouvernance | C5: Stratégie NR | D5: Des objectifs de réduction d'impact environnemental du numérique ont-ils été définis ? | G5: Non | H5: Des objectifs spécifiques sont définis mais ils ne sont pas suivis | I5: Des objectifs spécifiques sont définis et suivis dans le cadre d'une démarche RSE centrale | J5: Des objectifs spécifiques sont définis et suivis au niveau du pôle numérique responsable
A6: 1 | B6: 1. Stratégie et Gouvernance | C6: Stratégie NR | D6: Quelle serait la principale raison qui vous motiverait à inclure des principes Numérique responsable au sein de la collectivité ? | G6: Aucune raison particulière | H6: Des raisons juridiques (l'obligation juridique de se conformer aux régulations environnementales) | I6: La motivation de construire une image plus positive de la collectivité | J6: Le souhait de devenir un acteur actif et leader de changement societal
A7: 2 | B7: 1. Stratégie et Gouvernance | C7: Stratégie NR | D7: Pilotez-vous des indicateurs de mesure spécifique au numérique responsable ? (label?)
A8: 1 | B8: 1. Stratégie et Gouvernance | C8: Stratégie NR | D8: La stratégie numérique responsable de l'entreprise est-elle déclinée dans chaque entité (DSI, achats, métiers…) ? | G8: Non | H8: Des consignes génériques sont définies au niveau NR et suivies par les entités | I8: Des objectifs et consignes spécifiques à chaque entités sont définies au niveau NR | J8: Des objectifs sont définis pour chaque entité au niveau NR, les entités définissent chacune leur stratégie NR
A9: 1 | B9: 1. Stratégie et Gouvernance | C9: Stratégie NR | D9: La stratégie numérique responsable a-t-elle été déclinée dans d'autres documents programmatiques (SPASER, PCAET…) ? | G9: Non | H9: Oui, partiellement | I9: Oui, en grande partie | J9: Oui ils sont totalement inclus
A10: 1 | B10: 1. Stratégie et Gouvernance | C10: Stratégie NR | D10: Avez-vous un budget spécifique dédié pour une stratégie et des actions Numérique Responsable ? | G10: Non | H10: Utilisation de l'enveloppe de la DSI/Service | I10: Enveloppe dédiée dans la direction concernée | J10: Enveloppe dédiée au niveau transverse
A11: 2 | B11: 1. Stratégie et Gouvernance | C11: Stratégie NR | D11: Comment est réparti le budget Numérique responsable (formations, développement de use cases, enablers IT, autres) ?
A12: 3 | B12: 1. Stratégie et Gouvernance | C12: Stratégie NR | D12: Votre stratégie Numérique Responsable a-t-elle permis la mise en place de partenariats, la signature d'accords ou l'attribution de certifications / prix ? | G12: Non | H12: Non mais certaines opportunités ont été identifiées pour la mise en place de partenariats / accords | I12: La collectivité a mis en place des partenariats ou s'est déjà engagée via des accords sur sa stratégie NR | J12: La collectivité a été distinguée par des certifications / prix sur son investissement NR
A13: 3 | B13: 1. Stratégie et Gouvernance | C13: Stratégie NR | D13: Si oui, décrivez les partenariats, accords ou certifications | E13: Question qualitative entretien
A14: 2 | B14: 1. Stratégie et Gouvernance | C14: Stratégie NR | D14: Des objectifs de Numérique responsable sont-ils intégrés à vos rapport annuels ? | G14: Non | H14: Oui, partiellement (inclus dans les objectifs et la stratégie de l'organisation, mais pas détaillé dans la partie comptabilité) | I14: Oui, en grande partie (inclus dans les objectifs et la stratégie de de l'organisation et partiellement inclus dans la partie comptabilité) | J14: Oui ils sont totalement inclus dans les rapports annuels (ils font intégralement partie des bilans financiers consolidés, ils sont définis dans les objectifs de l'organisation et ils ont leur propre partie dans le rapport annuel de l'organisation)
A15: 2 | B15: 1. Stratégie et Gouvernance | C15: Stratégie NR | D15: Si oui, décrivez les éléments essentiels et l'année de mise en oeuvre ? | E15: Question qualitative entretien
A16: 1 | B16: 1. Stratégie et Gouvernance | C16: Org. Interne | D16: Dans votre organisation, cette dimension écologique du numérique est intégrée comme : … | G16: N'est pas intégrée | H16: Une fonction DSI | I16: Une fonction "Transition écologique" attachée au DGS | J16: Une fonction transverse rattachée au DGS
A17: 1 | B17: 1. Stratégie et Gouvernance | C17: Org. Interne | D17: Qui est en charge de porter les sujets Numérique Responsable au sein de votre organisation ? | G17: Personne n'est en charge | H17: Une personne porte ces sujets au sein d'une direction | I17: Une personne/une entité est en charge de l'ensemble des sujets Numérique Responsable à temps partiel | J17: Une ou plusieurs personn(e)s occupent un poste à temps plein dédié au Numérique Responsable
A18: 2 | B18: 1. Stratégie et Gouvernance | C18: Org. Interne | D18: A quel niveau hiérarchique se situe le pôle Numérique Responsable ? | G18: Pas de pôle Numérique Responsable | H18: Le pôle Numérique Responsable n'est pas visible dans la hiérarchie | I18: Le pôle Numérique Responsable est rattaché au niveau d'une Unité Business / Organisationnelle | J18: Le pôle Numérique Responsable est rattaché au niveau du DGS/de la Direction générale
A19: 2 | B19: 1. Stratégie et Gouvernance | C19: Org. Interne | D19: Le responsable numérique responsable participe t-il à des comités de pilotage ? | G19: Non | H19: Oui, en interne de son service | I19: Oui, en interne de sa direction | J19: Oui, en transverse sur l'ensemble de la collectivité
A20: 2 | B20: 1. Stratégie et Gouvernance | C20: Org. Interne | D20: Le pôle Numérique Responsable peut il s'appuyer sur des relais identifiés dans les entités ? | G20: Non | H20: Un groupe de contacts permet de partager quelques informations avec le pôle Numérique Responsable (veille, …) | I20: Des relais diffusent une veille et des bonnes pratiques Numérique Responsable au sein des entités | J20: Des représentants officiels (champions) du numérique responsable sont identifiés dans les différentes entités et ont une charge dédiée à cette thématique
A21: 3 | B21: 1. Stratégie et Gouvernance | C21: Org. Interne | D21: Faites-vous appel à des prestataires spécialisés dans le Numérique Responsable ? | G21: Non | H21: Des prestataires potentiels ont déjà été identifiés | I21: Des discussions ont été engagées avec des prestataires potentiels | J21: Des prestataires ont déjà été sollicités pour accompagner la collectivité
A22: 1 | B22: 1. Stratégie et Gouvernance | C22: Org. Interne | D22: Votre organisation a t-elle mis en place le télétravail hors crise sanitaire ? | G22: Non | J22: Oui
A23: 1 | B23: 1. Stratégie et Gouvernance | C23: Org. Interne | D23: Quelle est la part de télétravailleurs ? | G23: <10% | H23: 10%<X<40% | I23: 40%<X<70% | J23: >70%
A24: 1 | B24: 1. Stratégie et Gouvernance | C24: Org. Interne | D24: Quel est le nombre de jours télétravaillés par mois et par collaborateur en moyenne ? | G24: <4 | H24: 4<X<8 | I24: 8<X<12 | J24: >12
A25: 1 | B25: 1. Stratégie et Gouvernance | C25: Org. Interne | D25: Quelles difficultés avez-vous eu au sujet du télétravail ? (organisation du travail, matériel, sécurité, logiciels, réseau...)
A26: 2 | B26: 1. Stratégie et Gouvernance | C26: Org. Interne | D26: Est-ce que la politique de télétravail mise en place dans l'organisation a prévu une campagne de mesure des impacts environnementaux ? | G26: Non | J26: Oui
A27: 2 | B27: 1. Stratégie et Gouvernance | C27: AVEC/BYOD | D27: Mettez-vous en place une stratégie "AVEC" pour l'équipement informatique type ordinateur portable ? | G27: Non
A28: 2 | B28: 1. Stratégie et Gouvernance | C28: AVEC/BYOD | D28: Mettez-vous en place une stratégie "AVEC" pour l'équipement téléphonique type smartphone ? | G28: Non
A29: 2 | B29: 1. Stratégie et Gouvernance | C29: AVEC/BYOD | D29: En cas d'application d'une stratégie "AVEC", quelle stratégie avez-vous mis en place pour la faire accepter par les agents ?
A30: 1 | B30: 1. Stratégie et Gouvernance | C30: Mesure d'impact environnemental | D30: Souhaitez-vous avoir un outil de suivi et de pilotage de la performance environnementale du SI ? | G30: Non | J30: Oui
A31: 2 | B31: 1. Stratégie et Gouvernance | C31: Mesure d'impact environnemental | D31: Quel est le niveau d’urgence de votre besoin en outils ou méthodologies de mesure ? | E31: Faible / Moyen / élevé
A32: 2 | B32: 1. Stratégie et Gouvernance | C32: Mesure d'impact environnemental | D32: Quelles sont vos priorités ? (choix multiples) | E32: Se faire accompagner / Se former / Outiller / Mesurer / Suivre
A33: 2 | B33: 1. Stratégie et Gouvernance | C33: Mesure d'impact environnemental | D33: Si autres priorités, précisez :
A34: 1 | B34: 1. Stratégie et Gouvernance | C34: Sources | D34: De quelles sources proviennent les bonnes pratiques liées au Numérique Responsable mises en place par la collectivité (réglementation, organismes d'autorité, propres initiatives…)? | G34: La collectivité applique principalement la réglementation | H34: La collectivité s'appuie sur les préconisations d'organismes reconnus comme l'Ademe, le club Green IT… | I34: La collectivité participe à des démarches exploratoires sur certains leviers | J34: La collectivité expérimente des leviers et fait figure de précurseur
A35: 1 | B35: 1. Stratégie et Gouvernance | C35: Stratégie générale | D35: Avez-vous mis en œuvre une stratégie de Smart City ? | G35: Non | H35: Non, c'est un projet | I35: Oui, mais sur des actions isolées | J35: Oui, avec une stratégie globale
A36: 1 | B36: 1. Stratégie et Gouvernance | C36: Territoire | D36: Selon vous qui sont les acteurs en interne ou externe à votre structure, qui peuvent réduire les impacts écologiques du numérique ?
A37: 1 | B37: 1. Stratégie et Gouvernance | C37: Territoire | D37: Avez-vous directement ou indirectement des moyens d'agir sur ces acteurs ?
A38: 1 | B38: 1. Stratégie et Gouvernance | D38: Pourriez-vous fournir des exemples de mesures/projets/initiatives mis en place concernant le Numérique responsable ?

Sheet 2. Mesure
A1: Grille d'entretien | G1: Grille de notation
A2: Niveau | B2: Pilier | C2: Thématique | D2: Question | E2: Types de réponses | F2: Acteur répondant | G2: 1 | H2: 2 | I2: 3 | J2: 4 | K2: 5 | L2: 6
A3: 1 | B3: 2. Mesure | C3: Utilisateurs | D3: Quel est le nombre d'agents de la collectivité concernés par vos services numériques ? | F3: DSI
A4: 1 | B4: 2. Mesure | C4: Equipements | D4: Nombre d'unités centrales | E4: En unités | F4: DSI
A5: 1 | B5: 2. Mesure | C5: Equipements | D5: Nombre de PC portables | E5: En unités | F5: DSI
A6: 2 | B6: 2. Mesure | C6: Equipements | D6: Nombre de tablettes | E6: En unités | F6: DSI
A7: 3 | B7: 2. Mesure | C7: Equipements | D7: Nombre de téléphone IP | E7: En unités | F7: DSI
A8: 1 | B8: 2. Mesure | C8: Equipements | D8: Nombre de smartphones | E8: En unités | F8: DSI
A9: 3 | B9: 2. Mesure | C9: Equipements | D9: Nombre de bornes WIFI | E9: En unités | F9: DSI
A10: 3 | B10: 2. Mesure | C10: Equipements | D10: Nombre d'enceintes | E10: En unités | F10: DSI
A11: 1 | B11: 2. Mesure | C11: Equipements | D11: Nombre écran plat | E11: En unités | F11: DSI
A12: 2 | B12: 2. Mesure | C12: Equipements | D12: Nombre d'écran TV | E12: En unités | F12: DSI
A13: 2 | B13: 2. Mesure | C13: Equipements | D13: Taille moyenne des écrans | E13: en pouces | F13: DSI
A14: 1 | B14: 2. Mesure | C14: Equipements | D14: Nombre imprimantes en réseau | E14: en unité | F14: DSI
A15: 1 | B15: 2. Mesure | C15: Equipements | D15: Nombre imprimantes personnelles | E15: en unité | F15: DSI
... A17: 1 | B17: 2. Mesure | C17: Equipements | D17: Nombre de nouveaux outils / logiciels introduits dans votre organisation par an | E17: En unités | F17: DSI
A18: 1 | B18: 2. Mesure | C18: Equipements | D18: Des outils collaboratifs sont-ils utilisés par les agents ? | G18: Non, la collaboration se fait par mail uniquement | H18: Les agents ont accès à des espaces de stockages partagés | I18: Les agents ont accès à des outils collaboratifs | J18: Les agents ont accès à des outils collaboratifs et sont formés/sensibilisés à une utilisation responsable
A19: 1 | B19: 2. Mesure | C19: Equipements | D19: Quels sont les outils collaboratifs utilisés par vos agents ?
A20: 1 | B20: 2. Mesure | C20: Durée de vie | D20: Quelle est la durée de vie moyenne de vos unités centrales | F20: DSI | G20: <1 an | H20: 1 et 2 ans | I20: 2 et 3 ans | J20: 3 et 5 ans | K20: 5 et 7 ans | L20: >7 ans
A21: 1 | B21: 2. Mesure | C21: Durée de vie | D21: Quelle est la durée de vie moyenne de vos ordinateurs portables ? | F21: DSI | G21: <1 an | H21: 1 et 2 ans | I21: 2 et 3 ans | J21: 3 et 5 ans | K21: 5 et 7 ans | L21: >7 ans
A22: 2 | B22: 2. Mesure | C22: Durée de vie | D22: Quelle est la durée de vie moyenne de vos tablettes | F22: DSI | G22: <1 an | H22: 1 et 2 ans | I22: 2 et 3 ans | J22: 3 et 5 ans | K22: 5 et 7 ans | L22: >7 ans
A23: 2 | B23: 2. Mesure | C23: Durée de vie | D23: Quelle est la durée de vie moyenne de vos imprimantes personnelles | F23: DSI | G23: <1 an | H23: 1 et 2 ans | I23: 2 et 3 ans | J23: 3 et 5 ans | K23: 5 et 7 ans | L23: >7 ans
A24: 2 | B24: 2. Mesure | C24: Durée de vie | D24: Quelle est la durée de vie moyenne de vos imprimantes en réseau | F24: DSI | G24: <1 an | H24: 1 et 2 ans | I24: 2 et 3 ans | J24: 3 et 5 ans | K24: 5 et 7 ans | L24: >7 ans
A25: 2 | B25: 2. Mesure | C25: Durée de vie | D25: Quelle est la durée de vie moyenne de vos serveurs physiques | F25: DSI | G25: <1 an | H25: 1 et 2 ans | I25: 2 et 3 ans | J25: 3 et 5 ans | K25: 5 et 7 ans | L25: >7 ans
A26: 3 | B26: 2. Mesure | C26: Durée de vie | D26: Quelle est la durée de vie moyenne de vos téléphones IP | F26: DSI | G26: <1 an | H26: 1 et 2 ans | I26: 2 et 3 ans | J26: 3 et 5 ans | K26: 5 et 7 ans | L26: >7 ans
A27: 3 | B27: 2. Mesure | C27: Durée de vie | D27: Quelle est la durée de vie moyenne de vos bornes WIFI ? | F27: DSI | G27: <1 an | H27: 1 et 2 ans | I27: 2 et 3 ans | J27: 3 et 5 ans | K27: 5 et 7 ans | L27: >7 ans
A28: 3 | B28: 2. Mesure | C28: Durée de vie | D28: Quelle est la durée de vie moyenne de vos enceintes | F28: DSI | G28: <1 an | H28: 1 et 2 ans | I28: 2 et 3 ans | J28: 3 et 5 ans | K28: 5 et 7 ans | L28: >7 ans
A29: 1 | B29: 2. Mesure | C29: Empreinte environnementale du SI | D29: L'empreinte environnementale de votre SI, ou de votre projet, a-t-elle été évaluée au moins une fois ? | F29: DSI | G29: Non | H29: Une fois | I29: Ponctuellement mais régulièrement | J29: Suivi régulier
A30: 3 | B30: 2. Mesure | C30: Empreinte environnementale du SI | D30: Quels indicateurs sont suivis pour l'évaluation de votre empreinte environnementale du SI ? | E30: Veuillez écrire votre texte | F30: DSI
A31: 3 | B31: 2. Mesure | C31: Empreinte environnementale du SI | D31: Quels référentiels ou base de données environnementaux utilisez-vous pour faire cette évaluation ? | E31: Veuillez écrire votre texte | F31: DSI
A32: 3 | B32: 2. Mesure | C32: Empreinte environnementale du SI | D32: Avez-vous mesuré cette empreinte en interne collectivité ou en ayant recours à un bureau d'étude spécialisé ? | G32: En interne collectivité | H32: En ayant recours à un prestataire
A33: 3 | B33: 2. Mesure | C33: Empreinte environnementale du SI | D33: Utilisez-vous le RGESN ? Le protocole GHG ? | G33: Non, connaît pas | H33: Non, mais connu | I33: Oui, mais pas utilisé | J33: Oui, utilisé
A34: 1 | B34: 2. Mesure | C34: Empreinte environnementale du SI | D34: Etes-vous familiez avec l'Analyse du Cycle de Vie (ACV) ? | G34: Non, connaît pas | H34: Non, mais connu | I34: Oui, mais pas utilisé | J34: Oui, utilisé
A35: 2 | B35: 2. Mesure | C35: Empreinte environnementale du SI | D35: Si vous évaluez l'empreinte environnemental de votre SI, avez-vous une stratégie de mesure basée sur une ACV (analyse du cycle de vie) ? | E35: oui/non/non concernée | F35: DSI | G35: Non, connaît pas | H35: Non, mais connu | I35: Oui, mais pas utilisé | J35: Oui, utilisé
A36: 2 | B36: 2. Mesure | C36: Empreinte environnementale du SI | D36: Si oui, précisez le contenu de cette stratégie avec ACV ? | E36: Veuillez écrire votre texte | F36: DSI
A37: 1 | B37: 2. Mesure | C37: Empreinte environnementale du SI | D37: Avez-vous réalisé un bilan carbone ? | G37: Non | H37: Non, mais souhait de le faire | I37: Oui, mais incomplet et non suivi d'actions | J37: Oui, régulièrement et inséré dans une stratégie de la CT
A38: 1 | B38: 2. Mesure | C38: Empreinte environnementale du SI | D38: Publiez-vous votre BEGES ? | G38: Non
A39: 3 | B39: 2. Mesure | C39: Empreinte environnementale du SI | D39: Evaluez-vous les émissions directes de GES (ou SCOPE 1) ? Émissions directes provenant des installations fixes ou mobiles situées à l’intérieur du périmètre organisationnel. | E39: oui/non | F39: DSI
A40: 3 | B40: 2. Mesure | C40: Empreinte environnementale du SI | D40: Evaluez-vous les émissions à énergie indirectes (ou SCOPE 2) ? Émissions indirectes associées à la production d’électricité, de chaleur ou de vapeur importée pour les activités de l’organisation. | E40: oui/non | F40: DSI
A41: 3 | B41: 2. Mesure | C41: Empreinte environnementale du SI | D41: Evaluez-vous les autres émissions indirectes (ou SCOPE 3) ? Les autres émissions indirectement produites par les activités de l’organisation qui ne sont pas comptabilisées au 2 mais qui sont liées à la chaîne de valeur complète comme par exemple : l’achat de matières premières, fabrication des équipements informatiques, de services ou autres produits, déplacements des salariés, transport amont et aval des marchandises, gestions des déchets générés par les activités de l’organisme, utilisation et fin de vie des produits et services vendus, immobilisation des biens et équipements de productions… | E41: oui/non | F41: DSI
A42: 2 | B42: 2. Mesure | C42: Empreinte environnementale du SI | D42: Quels outils utilisez-vous pour mesurer la performance environnementale d'un service numérique (application ou site web) ? | E42: Veuillez écrire votre texte | F42: DSI
A43: 2 | B43: 2. Mesure | C43: Datacentre | D43: Quel est le volume global de stockage de vos données en moyenne sur l'année dernière (disques durs externes, serveurs, NAS, SAN) ? | E43: en To | F43: DSI
A44: 1 | B44: 2. Mesure | C44: Datacentre | D44: Disposez-vous d'une salle dédiée pour votre infrastructure informatique ? | E44: * Oui, une salle équipée d'équipements IT (serveurs, réseaux), onduleurs et climatiseurs * Oui, un placard sans aucun système spécifique * Non | F44: DSI
A45: 1 | B45: 2. Mesure | C45: Datacentre | D45: Votre salle informatique est | F45: DSI | G45: Interne
A46: 3 | B46: 2. Mesure | C46: Datacentre | D46: Quelle est la superficie totale de vos salles informatiques | E46: en m2 | F46: DSI
A47: 2 | B47: 2. Mesure | C47: Datacentre | D47: Quel est le niveau de performance énergétique de votre datacenter (PUE) ? | F47: DSI | G47: >2,5 | H47: Entre 1,8 et 2,5 | I47: Entre 1,4 et 1,8 | J47: <1,4
A48: 2 | B48: 2. Mesure | C48: Datacentre | D48: Quel est le nombre de serveurs physiques dans l'organisation ? | E48: Il est attendu une réponse avec un nombre de serveurs | F48: DSI
A49: 2 | B49: 2. Mesure | C49: Datacentre | D49: Quelle est l'évolution cette année en %, du nombre de serveurs physiques ? | E49: Il est attendu une réponse avec un nombre de serveurs | F49: DSI
A50: 2 | B50: 2. Mesure | C50: Datacentre | D50: Quel est le nombre de serveurs virtuels dans l'organisation ? | E50: Il est attendu une réponse avec un nombre de serveurs | F50: DSI
A51: 2 | B51: 2. Mesure | C51: Datacentre | D51: Quelle est l'évolution cette année en %, du nombre de serveurs virtuels ? | E51: Il est attendu une réponse avec un pourcentage | F51: DSI
A52: 2 | B52: 2. Mesure | C52: Datacentre | D52: Pilotez-vous l'usage et la consommation de vos serveurs ? | E52: Il est attendu une réponse avec un pourcentage | G52: Non | H52: La consommation électrique est pilotée | I52: Plusieurs indicateurs sont en place (consommation électrique, taux d'utilisation…) | J52: Plusieurs indicateurs sont en place (consommation électrique, taux d'utilisation…) et ont donné lieux a des actions correctives
A53: 1 | B53: 2. Mesure | C53: Datacentre | D53: Combien de datacenter sont-ils présents sur votre territoire ?

Sheet 3. Achat
A1: Grille d'entretien | G1: Grille de notation
A2: Niveau | B2: Pilier | C2: Thématique | D2: Question | E2: Types de réponses | F2: Acteur répondant | G2: 1 | H2: 2 | I2: 3 | J2: 4
A3: 1 | B3: 3. Achat | C3: Achat d'équipements | D3: Une démarche d’achats responsables des équipements numériques est-elle mise en place ? | E3: oui/non | G3: Non | J3: Oui
A4: 2 | B4: 3. Achat | C4: Achat d'équipements | D4: Publiez-vous un SPASER ? | G4: Non, nous ne sommes pas concernés | J4: Oui
A5: 2 | B5: 3. Achat | C5: Achat d'équipements | D5: Si oui, précisez les critères environnementaux retenus et le cas échéant les questions posées sur le volet développement durable ? | E5: Veuillez écrire votre texte
A6: 2 | B6: 3. Achat | C6: Achat d'équipements | D6: Communiquez-vous auprès de vos fournisseurs sur l’importance de la prise en compte des clauses environnementales et sociales dans votre phase de sourcing ? | E6: oui/non
A7: 1 | B7: 3. Achat | C7: Achat d'équipements | D7: Intégrez-vous des clauses environnementales dans vos marchés d'achat d’équipements ? | G7: Non | J7: Oui
A8: 1 | B8: 3. Achat | C8: Achat d'équipements | D8: Si oui, précisez quelle est sa part dans la décision finale | E8: Il est attendu une réponse avec un pourcentage
A9: 3 | B9: 3. Achat | C9: Achat d'équipements | D9: Intégrez-vous des clauses sociales dans vos marchés ? | E9: oui/non
A10: 3 | B10: 3. Achat | C10: Achat d'équipements | D10: Si oui, précisez les critères sociaux retenus ? | E10: Veuillez écrire votre texte
A11: 3 | B11: 3. Achat | C11: Achat d'équipements | D11: Intégrez-vous des clauses environnementales et sociales dans vos appels d’offres de services et prestations intellectuelles ? | E11: oui/non
A12: 3 | B12: 3. Achat | C12: Achat d'équipements | D12: Pouvez vous lister des exemples de clauses environnementales et sociales qui, d'après vous, ont le plus de poids environnemental ? | E12: Veuillez écrire votre texte
A13: 1 | B13: 3. Achat | C13: Achat d'équipements | D13: Dissociez-vous le renouvellement des unités centrales des autres équipements (écran, clavier, souris) ? | G13: Non | J13: Oui
A14: 1 | B14: 3. Achat | C14: Achat d'équipements | D14: Avez-vous un plan d'action pour réduction du nombre d'équipements par personne et par an ? | G14: Non
A15: 1 | B15: 3. Achat | C15: Achat d'équipements | D15: Si oui, quels équipements et quelles actions sont mis en place ? | E15: réponse ouverte
A16: 1 | B16: 3. Achat | C16: Achat d'équipements | D16: Quelle est la part de l'achat de matériel informatique d'occasion ou reconditionné par rapport à l'achat de neuf ? | E16: Il est attendu une réponse avec un pourcentage
A17: 1 | B17: 3. Achat | C17: Achat d'équipements | D17: Si oui, pouvez-nous nous décrire les équipements concernés et les revendeurs retenus ? | E17: réponse ouverte
A18: 3 | B18: 3. Achat | C18: Achat d'équipements | D18: Quelle part de vos copieurs est issue d'une filière de reconditionnement ? | E18: Il est attendu une réponse avec un pourcentage
A19: 3 | B19: 3. Achat | C19: Achat d'équipements | D19: Quelle est la part des cartouches d'impression issue d'une filière de reconditionnement ? | E19: Il est attendu une réponse avec un pourcentage
A20: 3 | B20: 3. Achat | C20: Achat d'équipements | D20: Avez-vous une stratégie d'urbanisation ou d'achat des équipements non IT (climatisation, traitement de l'air, onduleurs…) selon des critères environnementaux ? | E20: oui/non/ne sais pas
A21: 3 | B21: 3. Achat | C21: Achat d'équipements | D21: Si oui, avez-vous des exemples ? | E21: Veuillez écrire votre texte
A22: 2 | B22: 3. Achat | C22: Achat d'équipements | D22: Choisissez-vous un prestataire d'hébergement ou opérateurs datacentres selon des critères de performance environnementale ? | E22: oui/non/ne sais pas
A23: 2 | B23: 3. Achat | C23: Achat d'équipements | D23: Si oui, quelles sont les critères retenus ? | E23: Veuillez écrire votre texte
A24: 2 | B24: 3. Achat | C24: Achat d'équipements | D24: Comment anticipez-vous les nouvelles réglementations sur le sujet (exemple la loi relative à la lutte contre le gaspillage et à l'économie circulaire) ? | E24: Veuillez écrire votre texte
A25: 1 | B25: 3. Achat | C25: Location | D25: Avez-vous mis en place une stratégie de location de matériels plutôt que d'achat ? | E25: oui/non
A26: 2 | B26: 3. Achat | C26: Location | D26: Pouvez-nous nous décrire les équipements concernés par la location, le % par rapport au parc global et les fournisseurs retenus ? | E26: Veuillez écrire votre texte
... A35: 2 | B35: 3. Achat | C35: Labels | D35: Si oui, laquelle ? | E35: Veuillez écrire votre texte
A36: 2 | B36: 3. Achat | C36: Impression | D36: Avez-vous des fournisseurs qui proposent des copieurs reconditionnés ? | G36: Ne sait pas | H36: Non | J36: Oui
A37: 2 | B37: 3. Achat | C37: Impression | D37: Si oui, quels sont les fournisseurs retenus ? | E37: Veuillez écrire votre texte
A38: 3 | B38: 3. Achat | C38: Impression | D38: Quelle part de papier recyclé utilisez-vous ? | E38: Il est attendu une réponse avec un pourcentage
A39: 3 | B39: 3. Achat | C39: Impression | D39: Quels labels de papier recyclé utilisez-vous ? | E39: réponse ouverte

Sheet 4. Conception
A1: Grille d'entretien | G1: Grille de notation
A2: Niveau | B2: Pilier | C2: Thématique | D2: Question | E2: Types de réponses | F2: Acteur répondant | G2: 1 | H2: 2 | I2: 3 | J2: 4
A3: 1 | B3: 4. Conception | C3: Conception | D3: Mettez-vous en œuvre des bonnes pratiques de conception de services numériques ? | G3: Non | H3: Non, mais sensibilisé | I3: Oui, ponctuellement | J3: Oui, généralisé
A4: 1 | B4: 4. Conception | C4: Conception | D4: Quelles sont vos bonnes pratiques de conception de services numériques ? | E4: Veuillez écrire votre texte
A5: 2 | B5: 4. Conception | C5: Conception | D5: Vos bonnes pratiques de conception de services numériques sont-elles liées à l'éco-conception de services numériques ? | G5: Ne sait pas | H5: Non | J5: Oui
A6: 2 | B6: 4. Conception | C6: Conception | D6: Si oui, quels référentiels ou bonnes pratiques utilisez-vous ? | E6: Veuillez écrire votre texte
A7: 1 | B7: 4. Conception | C7: Conception | D7: Une stratégie de gestion des données (durée de conservation et volume stocké) est-elle mise en place ? | G7: Non | J7: Oui
A8: 3 | B8: 4. Conception | C8: Conception | D8: Avez-vous travaillé sur la réduction du temps passé par un agent sur vos services numériques (le temps moyen pour obtenir une information ou faire une démarche) ? | E8: oui/non | G8: Non | J8: Oui
A9: 3 | B9: 4. Conception | C9: Conception | D9: Avez-vous travaillé sur la réduction du temps passé par un usager sur vos services numériques (le temps moyen pour obtenir une information ou faire une démarche) ? | E9: oui/non | G9: Non | J9: Oui
A10: 3 | B10: 4. Conception | C10: Conception | D10: Si oui, comment ? | E10: Veuillez écrire votre texte
A11: 1 | B11: 4. Conception | C11: Conception | D11: Quelle est la part de solutions open-source dans vos projets ? | E11: % | G11: <10% | H11: 10%<X<40% | I11: 40%<X<70% | J11: >70%
A12: 3 | B12: 4. Conception | C12: Conception | D12: Si vous en avez la responsabilité, concevez-vous une charte graphique responsable ? | G12: Non concerné | H12: Non | I12: En projet | J12: Oui, existante
A13: 3 | B13: 4. Conception | C13: Conception | D13: Si oui, avez-vous des exemples de points d'attention lors de la conception de charte graphique responsable ? | E13: Veuillez écrire votre texte
A14: 1 | B14: 4. Conception | C14: Conception | D14: Mobilisez-vous un chef de produit sur la conception de vos services numériques ? | G14: Non | H14: Parfois | I14: Souvent | J14: Toujours
A15: 1 | B15: 4. Conception | C15: Conception | D15: Mobilisez-vous un ou plusieurs designers UX sur la conception de vos services numériques ? | G15: Non | H15: Parfois | I15: Souvent | J15: Toujours
A16: 1 | B16: 4. Conception | C16: Conception | D16: Mobilisez-vous un chercheur usager sur la conception de vos services numériques ? | G16: Non | H16: Parfois | I16: Souvent | J16: Toujours
A17: 1 | B17: 4. Conception | C17: Conception | D17: Mobilisez-vous un expert accessibilité sur la conception de vos services numériques ? | G17: Non | H17: Parfois | I17: Souvent | J17: Toujours
A18: 2 | B18: 4. Conception | C18: Conception | D18: Avez-vous besoin d'un chef de produit, expert accessibilité, designer UX ou chercheur usager ? | G18: Non | J18: Oui
A19: 2 | B19: 4. Conception | C19: Conception | D19: Le RGAA est-il mis en œuvre ? | G19: Non | J19: Oui
A20: 2 | B20: 4. Conception | C20: Conception | D20: Si oui, avez-vous des exemples de bonnes pratiques mises en place ou un projet exemplaire lié à la mise en œuvre du RGAA ? | E20: Veuillez écrire votre texte
A21: 2 | B21: 4. Conception | C21: Conception | D21: La conformité au RGPD est-elle systématiquement mise en place ? | G21: Non | J21: Oui
A22: 2 | B22: 4. Conception | C22: Conception | D22: Si oui, comment ? | E22: Veuillez écrire votre texte
A23: 3 | B23: 4. Conception | C23: Méthodes de conception | D23: Quelle méthode de développement de logiciel utilisez-vous ? (Cycle en V, Scrum, Safe…) | E23: Veuillez écrire votre texte
A24: 1 | B24: 4. Conception | C24: Méthodes de conception | D24: Les usagers finaux (citoyens, agents, etc) sont-ils impliqués dans le processus de conception de vos services numériques ? | G24: Non | H24: Parfois | I24: Souvent | J24: Toujours
A25: 1 | B25: 4. Conception | C25: Méthodes de conception | D25: Si oui, comment ? | E25: Veuillez écrire votre texte
A26: 1 | B26: 4. Conception | C26: Méthodes de conception | D26: Tous les métiers sont-ils impliqués lors de la réflexion et la conception d'une fonctionnalité (métier, UX/UI, développeur, ops…) ? | G26: Non | H26: Parfois | I26: Souvent | J26: Toujours
A27: 2 | B27: 4. Conception | C27: Méthodes de conception | D27: Faites-vous une revue de conception systématique avant le développement ? | G27: Ne sait pas | H27: Non | J27: Oui
A28: 2 | B28: 4. Conception | C28: Méthodes de conception | D28: Faites-vous une revue de code systématique pendant le développement ? | G28: Ne sait pas | H28: Non | J28: Oui
A29: 2 | B29: 4. Conception | C29: Méthodes de conception | D29: Faites-vous un développement d'abord pour les terminaux mobiles, en adoptant une approche responsive ? | G29: Non | J29: Oui
A30: 1 | B30: 4. Conception | C30: Méthodes de conception | D30: Des solutions non-numérique plus efficientes ont t-elles été envisagées ? | G30: Non | J30: Oui
A31: 1 | B31: 4. Conception | C31: Méthodes de conception | D31: Si oui, avez-vous des exemples ? | E31: Veuillez écrire votre texte
A32: 1 | B32: 4. Conception | C32: Capacité réseau et matériel | D32: Avez-vous mis en place la possibilité d'une utilisation avec de faibles débits (2G/3G) de vos services numériques ? | G32: Non | H32: Parfois | I32: Souvent | J32: Toujours
A33: 1 | B33: 4. Conception | C33: Capacité réseau et matériel | D33: Avez-vous mis en place la possibilité d'une utilisation hors ligne de vos services numériques ? | G33: Non | H33: Parfois | I33: Souvent | J33: Toujours
A34: 2 | B34: 4. Conception | C34: Capacité réseau et matériel | D34: Testez-vous vos applications web sur des anciens navigateurs ? | G34: Non | H34: Parfois | I34: Souvent | J34: Toujours
A35: 2 | B35: 4. Conception | C35: Capacité réseau et matériel | D35: Quels sont les navigateurs et versions minimum cibles ? (exemple : IE10, Firefox v57...) | E35: Veuillez écrire votre texte
A36: 2 | B36: 4. Conception | C36: Capacité réseau et matériel | D36: Testez-vous vos applications sur des anciens équipements ? | G36: Non | H36: Parfois | I36: Souvent | J36: Toujours
A37: 2 | B37: 4. Conception | C37: Capacité réseau et matériel | D37: Quels sont les équipements et versions minimum cibles ? (exemple : Iphone 5, Samsung Galaxy S4…) | E37: Veuillez écrire votre texte
A38: 2 | B38: 4. Conception | C38: Capacité réseau et matériel | D38: Une réduction volontaire du poids des pages web est-elle mise en place ? | G38: Non | J38: Oui
A39: 2 | B39: 4. Conception | C39: Capacité réseau et matériel | D39: Une réduction volontaire du nombre de médias (images, vidéos) est-elle mise en place ? | G39: Non | J39: Oui
A40: 2 | B40: 4. Conception | C40: Capacité réseau et matériel | D40: Une réduction volontaire du volume de données collectées est-elle mise en place ? | G40: Non | J40: Oui
A41: 2 | B41: 4. Conception | C41: Capacité réseau et matériel | D41: Une réduction volontaire du volume de données transmises est-elle mise en place ? | G41: Non | J41: Oui
A42: 3 | B42: 4. Conception | C42: Capacité réseau et matériel | D42: Quelles sont les adaptations mises en place dans le service numérique et selon les possibilités du terminal ? (exemple : responsive image) | E42: Veuillez écrire votre texte
A43: 2 | B43: 4. Conception | C43: Equipements | D43: Consolidez-vous les serveurs physiques sous-utilisés pour les regrouper (rationalisation) ? | E43: oui/non/ne sais pas | G43: Ne sait pas | H43: Non | J43: Oui
A44: 1 | B44: 4. Conception | C44: Equipements | D44: Quelles sont les bonnes pratiques écoresponsables mises en place dans votre datacentre ? | E44: Veuillez écrire votre texte
A45: 2 | B45: 4. Conception | C45: Equipements | D45: Avez-vous mis en place une urbanisation de votre datacentre permettant de réduire ses impacts environnementaux, notamment dans une perspective d'évolution de ce datacentre ? | G45: Ne sait pas | H45: Non | J45: Oui
A46: 1 | B46: 4. Conception | C46: Equipements | D46: Vos projets utilisent-ils des objets connectés (iOT) ? | G46: Non | H46: Non, sauf 1-2 | I46: Oui, régulièrement | J46: Oui, une grande partie
A47: 1 | B47: 4. Conception | C47: Equipements | D47: Si oui, quels sont les objets connectés utilisés et leur nombre ? | E47: Veuillez écrire votre texte
A48: 2 | B48: 4. Conception | C48: Equipements | D48: Les équipements physiques du datacentre sont-ils mutualisés ? | G48: Ne sait pas | H48: Non | J48: Oui
A49: 3 | B49: 4. Conception | C49: Equipements | D49: Intégrez-vous le principe de l'économie de la fonctionnalité par exemple en proposant un service incluant la mise à disposition d'équipements à durée de vie longue, plutôt que la vente ? | G49: Ne sait pas | H49: Non | J49: Oui

Sheet 5. DEEE et Economie circulaire
A1: Grille d'entretien | G1: Grille de notation
A2: Niveau | B2: Pilier | C2: Thématique | D2: Question | E2: Types de réponses | F2: Acteur répondant | G2: 1 | H2: 2 | I2: 3 | J2: 4
A3: 1 | B3: 5. DEEE et Economie circulaire | C3: Recyclage | D3: Comment gérez-vous la fin de vie de vos équipements ? | G3: Les équipements en fin de vie sont jetés et remplacés quand ils ne sont plus assez performants | H3: Les équipements en fin de vie réparés dans la mesure du possible | I3: Les équipements en fin de vie sont récupérés par des prestataires écoresponsables | J3: Les équipements en fin de vie sont vendus/donnés pour être remis en circulation
A4: 2 | B4: 5. DEEE et Economie circulaire | C4: Recyclage | D4: Faites-vous reprendre vos DEEE par un éco-organisme ? | F4: DSI/Achat ? | G4: Non | H4: Non, mais c'est en projet | I4: Oui, mais que pour certains services | J4: Oui, la pratique est généralisée
A5: 2 | B5: 5. DEEE et Economie circulaire | C5: Recyclage | D5: Faites-vous reprendre vos DEEE par un système individuel ? | G5: Non | H5: Non, mais c'est en projet | I5: Oui, mais que pour certains services | J5: Oui, la pratique est généralisée
A6: 1 | B6: 5. DEEE et Economie circulaire | C6: Recyclage | D6: Avez-vous des bacs de collecte pour les deee de vos employés ? | G6: Non | H6: Non, mais c'est en projet | I6: Oui, mais que pour certains services | J6: Oui, la pratique est généralisée
A7: 2 | B7: 5. DEEE et Economie circulaire | C7: Recyclage | D7: Avez-vous prévu dans le choix de vos fournisseurs d’équipements électriques et électroniques (ordinateurs, imprimantes, cartouches, serveurs, smartphoines,…) des dispositions spécifiques à la gestion de la fin de vie ? | G7: Non | H7: Non, mais c'est en projet | J7: Oui
A8: 3 | B8: 5. DEEE et Economie circulaire | C8: Recyclage | D8: Quelles garanties demandez-vous à ces professionnels ? | E8: Veuillez écrire votre texte
A9: 1 | B9: 5. DEEE et Economie circulaire | C9: Recyclage | D9: Mettez-vous en place la collecte séparée des déchets de cartouches / toners ? | G9: Non | H9: Non, mais c'est un projet | I9: Oui, mais que pour certains services | J9: Oui, la pratique est généralisée
A10: 2 | B10: 5. DEEE et Economie circulaire | C10: Recyclage | D10: Vers quoi est dirigée la collecte des cartouches / toners ? | G10: Ne sait pas | H10: Filière de destruction | I10: Filière de recyclage | J10: Filière de reconditionnement et de recyclage en fonction
A11: 3 | B11: 5. DEEE et Economie circulaire | C11: Recyclage | D11: Avez-vous des prestataires qui s'occupent du recueil et de contrôle du Bordereau de suivi des déchets dangereux (BSDD) ? | G11: Ne sais pas | H11: Non | I11: Oui, prestataire externe | J11: Oui, internalisé
A12: 3 | B12: 5. DEEE et Economie circulaire | C12: Recyclage | D12: Si oui, lesquels ? | E12: Veuillez écrire votre texte
A13: 1 | B13: 5. DEEE et Economie circulaire | C13: Réemploi, économie circulaire | D13: Mettez-vous en place une stratégie pour entretenir les ordinateurs pour éviter qu'ils ralentissent et deviennent instables ? | G13: Ne sait pas | H13: Non | I13: Actions partielles | J13: Oui
A14: 1 | B14: 5. DEEE et Economie circulaire | C14: Réemploi, économie circulaire | D14: Faites-vous la mise à jour des équipements plutôt que de les remplacer ? | G14: Ne sait pas | H14: Non | I14: Partiellement | J14: Oui
A15: 1 | B15: 5. DEEE et Economie circulaire | C15: Réemploi, économie circulaire | D15: Faites-vous la remise en état pour réemploi plutôt que le recyclage ? | G15: Ne sait pas | H15: Non | I15: Partiellement | J15: Oui
A16: 1 | B16: 5. DEEE et Economie circulaire | C16: Réemploi, économie circulaire | D16: Pouvez-vous décrire un exemple ?
A17: 2 | B17: 5. DEEE et Economie circulaire | C17: Réemploi, économie circulaire | D17: Faites-vous la remise en état du matériel fonctionnel via un prestataire ? | G17: Ne sait pas | H17: Non | I17: Partiellement | J17: Oui
A18: 2 | B18: 5. DEEE et Economie circulaire | C18: Réemploi, économie circulaire | D18: Si oui, quels sont les équipements concernés et les opérateurs retenus ? | E18: Veuillez écrire votre texte
A19: 1 | B19: 5. DEEE et Economie circulaire | C19: Réemploi, économie circulaire | D19: Plus précisément, mettez-vous en place une démarche de réemploi des téléphones / smartphones ? | G19: Ne sait pas | H19: Non | I19: Partiellement | J19: Oui
A20: 1 | B20: 5. DEEE et Economie circulaire | C20: Réemploi, économie circulaire | D20: Avez-vous recours aux plateformes de dons ? | G20: Ne sait pas | H20: Non | I20: Partiellement | J20: Oui
A21: 1 | B21: 5. DEEE et Economie circulaire | C21: Réemploi, économie circulaire | D21: Si oui, à quelles plateformes faites vous les dons ? | E21: Veuillez écrire votre texte
A22: 2 | B22: 5. DEEE et Economie circulaire | C22: Réemploi, économie circulaire | D22: Réaffectez-vous les équipements informatiques ? | G22: Ne sait pas | H22: Non | I22: Partiellement | J22: Oui
A23: 2 | B23: 5. DEEE et Economie circulaire | C23: Réemploi, économie circulaire | D23: Si oui, pour quels publics et pour quels usages ? | E23: Veuillez écrire votre texte
A24: 3 | B24: 5. DEEE et Economie circulaire | C24: Réemploi, économie circulaire | D24: L'énergie thermique produite par les datacentres que vous utilisez est-elle réutilisée ? | G24: Ne sait pas | H24: Non | I24: Partiellement | J24: Oui
A25: 3 | B25: 5. DEEE et Economie circulaire | C25: Réemploi, économie circulaire | D25: Faites-vous un contrôle régulier des équipements numériques inutilisés afin de les décomissionner le cas échéant ? | G25: Ne sait pas | H25: Non | I25: Ponctuellement | J25: Oui
A26: 2 | B26: 5. DEEE et Economie circulaire | C26: Réemploi, économie circulaire | D26: Connaissez-vous les acteurs de reconditionné sur votre territoire ? | G26: Non | H26: 1 ou 2 principaux | I26: Les principaux | J26: Tous
A27: 2 | B27: 5. DEEE et Economie circulaire | C27: Réemploi, économie circulaire | D27: Cartographie des acteurs du reconditionné sur le territoire

Sheet 6. Sensibilisation
A1: Grille d'entretien | G1: Grille de notation
A2: Niveau | B2: Pilier | C2: Thématique | D2: Question | E2: Type de question | F2: Acteur répondant | G2: 1 | H2: 2 | I2: 3 | J2: 4
A3: 1 | B3: 6. Sensibilisation | C3: Information | D3: Connaissez-vous la boîte à outils Numérique responsable de la DINUM ? | G3: Non | H3: Non, mais entendu parlé | I3: Oui, mais sans l'utiliser | J3: Oui, et nous l'utilisons
A4: 1 | B4: 6. Sensibilisation | C4: Information | D4: Connaissez-vous la boîte à outils Numérique responsable de l'INR ? | G4: Non | H4: Non, mais entendu parlé | I4: Oui, mais sans l'utiliser | J4: Oui, et nous l'utilisons
A5: 1 | B5: 6. Sensibilisation | C5: Information | D5: Quelles sont les autres ressources NR que vous connaissez ?
A6: 2 | B6: 6. Sensibilisation | C6: Information | D6: Les engagements et initiatives de la collectivité sur le NR sont-ils valorisés auprès des agents et des citoyens ? | G6: Non, il n'y a pas de communication spécifique sur ces engagements/initiatives | H6: Les engagements/initiatives de la CT sont visibles sur le site | I6: Les engagments/initiatives de la CT font régulièrement l'objet de communications dédiées | J6: Les engagements/initiatives de la CT sont un élément clé de son image et de sa communication
A7: 1 | B7: 6. Sensibilisation | C7: Eco-gestes | D7: Vos collaborateurs manifestent-ils une volonté de changement des pratiques de l'entreprise en termes de Numérique Responsable ? | G7: Non | H7: Les agents montrent une prise de conscience et une responsabilité individuelle | I7: Les agents participent à la diffusion de bonnes pratiques en interne | J7: Les agents sont force de proposition pour diminuer l'impact environnemental de l'IT de l'entreprise
A8: 2 | B8: 6. Sensibilisation | C8: Eco-gestes | D8: Selon vous, vos agents adoptent-ils un comportement responsable sur le volet du numérique ? | G8: Non | H8: Ils appliquent les bonnes pratiques recommandées par la CT | I8: Ils adoptent individuellement un comportement responsable au-delà des recommandations de la CT | J8: Les agents échangent entre eux sur les bonnes pratiques pour assurer un comportement collectif responsable
A9: 2 | B9: 6. Sensibilisation | C9: Eco-gestes | D9: Selon vous qui sont les acteurs en interne à votre structure, qui peuvent réduire les impacts écologiques du numérique ? | E9: Veuillez écrire votre texte
A10: 2 | B10: 6. Sensibilisation | C10: Eco-gestes | D10: Avez-vous directement ou indirectement des moyens d'agir sur ces acteurs ? | G10: Non | J10: Oui
A11: 1 | B11: 6. Sensibilisation | C11: Eco-gestes | D11: Mettez-vous en place des campagnes de communication aux gestes clés d'une utilisation éco-responsable du numérique ? | G11: Non | H11: Non, mais en projet | I11: Oui, mais ponctuel dans un service/une direction | J11: Oui, c'est un sujet pris en compte dans la communication générale de la collectivité
A12: 1 | B12: 6. Sensibilisation | C12: Eco-gestes | D12: Si oui, ces supports sont accessibles et comment ? | G12: Ils ne sont pas accessibles | H12: Ils sont accessibles dans les archives de la com | I12: Ils sont accessibles sur le commun des agents | J12: Ils sont accessibles dans une rubrique dédiée sur le commun et sur le site de la collectivité
A13: 1 | B13: 6. Sensibilisation | C13: Eco-gestes | D13: Pouvez-vous nous transmettre ces supports ? | E13: Question entretien | F13: DSI/DIRCOM/DGS
A14: 2 | B14: 6. Sensibilisation | C14: Eco-gestes | D14: Avez-vous une stratégie d'émulation écologique (nudge) sur votre parc numérique (smartphones, imprimantes, ordinateurs) ? | E14: oui/non | G14: Ne sait pas | H14: Non | I14: Non, mais en projet | J14: Oui
A15: 2 | B15: 6. Sensibilisation | C15: Eco-gestes | D15: Si oui, quels choix avez-vous retenu ? | E15: Question entretien
A16: 1 | B16: 6. Sensibilisation | C16: Eco-gestes | D16: Quel est le mode de paramétrage par défaut de vos imprimantes ? | G16: Je ne sais pas | J16: Noir et blanc
A17: 1 | B17: 6. Sensibilisation | C17: Eco-gestes | D17: Avez-vous instauré une politique d'extinction du parc numérique sur des heures hors activité ? | G17: Non | H17: Non, pas souhaité | I17: Non, mais en cours de discussion | J17: Oui
A18: 2 | B18: 6. Sensibilisation | C18: Eco-gestes | D18: Rationalisez-vous l’usage de la messagerie, par exemple, en limitant le stockage serveur ? | G18: Non | H18: Non, pas souhaité | I18: Non, mais en cours de discussion | J18: Oui
A19: 2 | B19: 6. Sensibilisation | C19: Eco-gestes | D19: Désinstallez-vous régulièrement les logiciels inutilisés ? | G19: Non | H19: Non, même si sensibilisé | I19: Non, mais en cours de discussion | J19: Oui
A20: 1 | B20: 6. Sensibilisation | C20: Eco-gestes | D20: Quelle est votre politique de mise à jour des logiciels au sein de votre collectivité ? | G20: Aucune mise à jour | H20: Mise à jour des logiciels lorsqu'indispensable | I20: Mise à jour des logiciels de manière automatique | J20: Mise à jour des logiciels systématiquement à chaque nouvelle version
A21: 1 | B21: 6. Sensibilisation | C21: Eco-gestes | D21: Avez-vous mis en place un dispositif pour réduire le volume de données transportées via le mail notamment ? | G21: Non | H21: Non, même si ponctuellement nous utilisons des outils comme Wetransfer pour les gros volumes | I21: Oui, mais non utilisé par tous les agents | J21: Oui, et connu et utilisé par tous les agents
A22: 1 | B22: 6. Sensibilisation | C22: Eco-gestes | D22: Avez-vous mis en place un système de partage de document ? | G22: Non | H22: Non, même si ponctuellement nous utilisons des outils comme Wetransfer pour les gros volumes | I22: Oui, mais non utilisé par tous les agents | J22: Oui, et connu et utilisé par tous les agents
A23: 1 | B23: 6. Sensibilisation | C23: Eco-gestes | D23: Si oui, lequel ? | E23: Question entretien
A24: 2 | B24: 6. Sensibilisation | C24: Eco-gestes | D24: Avez-vous mis en place des dispositifs pour réduire les volumes stockées dans le temps ? | G24: Non | J24: Oui
A25: 2 | B25: 6. Sensibilisation | C25: Eco-gestes | D25: La mise à jour automatiques des applications est-elle activée par défaut sur vos smartphones fournis à vos collaborateurs ? | G25: Ne sait pas | H25: Non | J25: Oui
A26: 2 | B26: 6. Sensibilisation | C26: Eco-gestes | D26: La mise à jour automatiques de l'OS est-elle activée par défaut sur vos smartphones fournis à vos collaborateurs ? | G26: Ne sait pas | H26: Non | J26: Oui
A27: 1 | B27: 6. Sensibilisation | C27: Information agents | D27: Au-delà des communications sur les initiatives et engagements de la CT, veillez-vous à la sensibilisation et la compréhension de vos agents des enjeux du Numérique Responsable ? | G27: Non | H27: A quelques moments clés de leur vie professionnelle (recrutement, montée de grades, formations ou évènements…) | I27: Régulièrement via des communications | J27: Régulièrement via des communications, des évènements, des formations
A28: 2 | B28: 6. Sensibilisation | C28: Information agents | D28: Avez-vous mis en place une veille structurée sur les sujets Numérique Responsable (partenaires, bonnes pratiques, règlementation…) ? | G28: Non | H28: Une veille est réalisée ponctuellement selon les besoins | I28: Des agents sont en charge de réaliser cette veille régulièrement | J28: Une veille est réalisée en continu et est régulièrement transformée en actions concrètes
A29: 2 | B29: 6. Sensibilisation | C29: Information agents | D29: Selon votre estimation, dans quelles mesures vos agents sont ils au courant de vos initiatives et engagements Numérique Responsable ? | G29: Ils ne sont pas au courant | H29: Ils en sont informés mais ne sauraient pas en parler | I29: Une majorité des agents saurait présenter quelques initiatives / engagements | J29: Les agents sauraient chacun présenter quelques initiatives / engagements de manière détaillée
A30: 2 | B30: 6. Sensibilisation | C30: Information agents | D30: Les indicateurs de suivi liés à l'impact environnemental de l'IT sont-ils communiqués aux agents ? | G30: Non | H30: Certains KPI sont diffusés occasionnellement pour appuyer des messages | I30: Les KPI sont régulièrement diffusé à travers des communications spécifiques | J30: Ces KPI sont régulièrement partagés et sont accompagnés de compléments d'informations, objectifs, bonnes pratiques…
A31: 3 | B31: 6. Sensibilisation | C31: Information agents | D31: Par quels canaux les agents peuvent ils partager des propositions pour diffuser et faire adopter un comportement Numérique Responsable dans la CT ? | G31: Aucun canal n'existe | H31: Les agents peuvent s'investir dans des groupes de travail ou remonter des propositions via le management | I31: Un canal dédié permet aux agents de diffuser des bonnes pratiques ou de les remonter à des représentants Numérique Responsable | J31: Un canal dédié existe et un processus de traitement et de suivi des propositions est en place
A32: 1 | B32: 6. Sensibilisation | C32: Formation | D32: Sensibilisez-vous vos collaborateurs aux bonnes pratiques IT (éteindre les équipements, limiter l'envoi et le stockage excessif de données…) ? | G32: Il n'y a pas de sensibilisation mise en place | H32: Les bonnes pratiques sont diffusées régulièrement (au travers de communications, écrans de veille, chartes…) | I32: Les bonnes pratiques sont encouragées (au travers de challenges, évènements, formations…) | J32: Le respect des bonnes pratiques est fortement incité par les entités et le management d'équipes
A33: 1 | B33: 6. Sensibilisation | C33: Formation | D33: Avez-vous intégré des formations autour de la réduction des impacts environnemental du numérique dans votre plan de formation ? | G33: Non | H33: Non, formation sur demande des agents intéressés | I33: Non, même si formation commune ouverte à tous proposée | J33: Oui
A34: 2 | B34: 6. Sensibilisation | C34: Formation | D34: Combien de vos agents ont-ils déjà été formés spécifiquement sur ce sujet ? | E34: Unité | G34: <10% | H34: 10%<X<40% | I34: 40%<X<70% | J34: >70%
A35: 2 | B35: 6. Sensibilisation | C35: Formation | D35: Pour l'année 2023, combien de vos agents vont-ils être formés spécifiquement sur ce sujet ? | E35: Unité | G35: <10% | H35: 10%<X<40% | I35: 40%<X<70% | J35: >70%
A36: 2 | B36: 6. Sensibilisation | C36: Formation | D36: Combien de managers ont été formés sur le sujet du numérique responsable ? | E36: Unité | G36: <10% | H36: 10%<X<40% | I36: 40%<X<70% | J36: >70%
A37: 3 | B37: 6. Sensibilisation | C37: Formation | D37: Existe-t-il des objectifs et indicateurs sur le niveau de formation des agents sur les leviers Numérique Responsable ? | G37: Non | H37: Les participants aux formations sont suivis mais il n'y a pas d'objectifs définis | I37: Des objectifs de participation sont fixés et peuvent éventuellement être regardés pour des promotions / primes… | J37: Le niveau de maturité de chaque collaborateur sur ces sujets est tracé (via une certification par exemple)
A38: 2 | B38: 6. Sensibilisation | C38: Formation | D38: Vous assurez-vous de la montée en compétence de vos équipes sur les leviers Numérique Responsable (écoconception applicative, optimisation des infrastructures, gestion responsable du cloud, optimisation de l'architecture, virtualisation des serveurs…) ? | G38: Non | H38: Ces compétences ne sont pas développées en interne mais les messages clés sont communiqués de temps en temps aux agents | I38: Des formations / sensibilisations génériques sur le Numérique Responsable sont disponibles | J38: Des formations détaillées sont disponibles sur des leviers spécifiques
A39: 3 | B39: 6. Sensibilisation | C39: Formation | D39: Les compétences / expériences sur le Numérique responsable sont elles valorisées au niveau du recrutement ? | G39: Non | H39: Ces compétences / expériences sont valorisées si le candidat les met en avant et/ou si elles correspondent au besoin recherché | I39: Ces compétences / expériences sont recherchées chez les candidats | J39: Des postes sont ouverts spécifiquement pour acquérir ces compétences dans la CT
A40: 3 | B40: 6. Sensibilisation | C40: Formation | D40: Les compétences / expériences sur le Numérique responsable sont elles valorisées au cours de l'évolution d'un collaborateur dans l'entreprise ? | G40: Non | H40: Le développement d'un agent via des formations est reconnu de manière générale | I40: Ces compétences sont reconnues comme des compétences stratégiques pour un agent | J40: Le développement de ces compétences peut constituer un prérequis pour certains grades
A41: 3 | B41: 6. Sensibilisation | C41: Formation | D41: Quel type de formation souhaitez-vous pour vos collaborateurs ? | E41: Formation courte (<= 1 j) / Formation longue (2 jours et plus)
A42: 1 | B42: 6. Sensibilisation | C42: Territoire/Eco-gestes | D42: Selon vous qui sont les acteurs sur votre territoire qui peuvent réduire les impacts écologiques du numérique ? | E42: Veuillez écrire votre texte
A43: 2 | B43: 6. Sensibilisation | C43: Territoire/Information aux externes | D43: Informez-vous vos utilisateurs sur les impacts environnementaux de l'usage de vos services numériques ?
A44: 2 | B44: 6. Sensibilisation | C44: Territoire/Information aux externes | D44: Avez-vous mis en place des actions de sensibilisation des habitants de votre territoire aux écogestes numériques ?
A45: 2 | B45: 6. Sensibilisation | C45: Territoire/Eco-gestes | D45: Si oui, donnez un exemple
A46: 2 | B46: 6. Sensibilisation | C46: Territoire/Information aux externes | D46: Avez-vous déjà entrepris des actions de sensibilisation auprès des entreprises et associations du territoire ?
A47: 2 | B47: 6. Sensibilisation | C47: Territoire/Eco-gestes | D47: Si oui, donnez des exemples
A48: 3 | B48: 6. Sensibilisation | C48: Territoire/Information aux externes | D48: Le pôle développement économique de votre collectivité, en lien avec les entreprises, est-il senbilisé aux enjeux du numérique responsable ? | G48: Non | H48: Quelques fois | I48: Sur la majorité de nos services numériques | J48: Sur tous les services
